<nfeProc versao="4.00" xmlns="http://www.portalfiscal.inf.br/nfe"><NFe xmlns="http://www.portalfiscal.inf.br/nfe"><infNFe Id="NFe31210817159518000175550010033629631743766978" versao="4.00"><ide><cUF>31</cUF><cNF>74376697</cNF><natOp>Venda producao do estabelecimento / Vnd prod.est.opr.c/pr.s</natOp><mod>55</mod><serie>1</serie><nNF>3362963</nNF><dhEmi>2021-08-03T04:50:12-03:00</dhEmi><dhSaiEnt>2021-08-03T04:50:12-03:00</dhSaiEnt><tpNF>1</tpNF><idDest>1</idDest><cMunFG>3118601</cMunFG><tpImp>1</tpImp><tpEmis>1</tpEmis><cDV>8</cDV><tpAmb>1</tpAmb><finNFe>1</finNFe><indFinal>0</indFinal><indPres>9</indPres><indIntermed>0</indIntermed><procEmi>0</procEmi><verProc>SAP GRC NFE 10.0</verProc></ide><emit><CNPJ>17159518000175</CNPJ><xNome>Domingos Costa Industrias Alimentic S/A</xNome><xFant>Domingos Costa Ind. Alim. S.A</xFant><enderEmit><xLgr>Pca. Louis Ensch</xLgr><nro>160</nro><xBairro>CIDADE INDUSTRIAL</xBairro><cMun>3118601</cMun><xMun>CONTAGEM</xMun><UF>MG</UF><CEP>32210050</CEP><cPais>1058</cPais><xPais>Brasil</xPais><fone>3133683300</fone></enderEmit><IE>1860015820028</IE><CRT>3</CRT></emit><dest><CNPJ>23399397000131</CNPJ><xNome>ENIO CAMPOS ME</xNome><enderDest><xLgr>RUA PROFESSORA LIBANIA LEMOS</xLgr><nro>475</nro><xCpl>LETRA A</xCpl><xBairro>SAO GONCALO</xBairro><cMun>3118304</cMun><xMun>CONSELHEIRO LAFAIETE</xMun><UF>MG</UF><CEP>36409600</CEP><cPais>1058</cPais><xPais>Brasil</xPais><fone>3198223956</fone></enderDest><indIEDest>1</indIEDest><IE>1835568870074</IE></dest><det nItem="1"><prod><cProd>000000000000210124</cProd><cEAN>17896417201112</cEAN><xProd>FARINHA C/FERMENTO VILMA PLAST. 10X1_DOC</xProd><NCM>11010010</NCM><CEST>1704418</CEST><CFOP>5101</CFOP><uCom>FD</uCom><qCom>2.0000</qCom><vUnCom>39.4000000000</vUnCom><vProd>78.80</vProd><cEANTrib>7896417201115</cEANTrib><uTrib>UN</uTrib><qTrib>2.0000</qTrib><vUnTrib>39.4000000000</vUnTrib><indTot>1</indTot></prod><imposto><ICMS><ICMS20><orig>0</orig><CST>20</CST><modBC>3</modBC><pRedBC>61.1100</pRedBC><vBC>30.65</vBC><pICMS>18.0000</pICMS><vICMS>5.52</vICMS></ICMS20></ICMS><IPI><cEnq>999</cEnq><IPINT><CST>01</CST></IPINT></IPI><PIS><PISNT><CST>08</CST></PISNT></PIS><COFINS><COFINSNT><CST>08</CST></COFINSNT></COFINS></imposto><infAdProd>Reducao da base/Isencao ou nao sujeicao a IPI/RED. B.C CONF. ART 43 E ALIENA A1, ITEM 20 DO ANEXO IV DEC. 43080/02/PRAZO DE VALIDADE DE 10 (DEZ) DIAS, IMPRORROGAVEL, RE/PTA No 45.000012147-21 DF CONTAGEM/TOTAL VFCP = R$ 0.00 E VFCPST = R$ 0.00 Codigo do CIOT: 125043719281/8309</infAdProd></det><det nItem="2"><prod><cProd>000000000000210131</cProd><cEAN>17896417201044</cEAN><xProd>FARINHA ESPECIAL VILMA PLASTICO 10X1_DOC</xProd><NCM>11010010</NCM><CEST>1704400</CEST><CFOP>5101</CFOP><uCom>FD</uCom><qCom>10.0000</qCom><vUnCom>36.4820000000</vUnCom><vProd>364.82</vProd><cEANTrib>7896417201047</cEANTrib><uTrib>UN</uTrib><qTrib>10.0000</qTrib><vUnTrib>36.4820000000</vUnTrib><indTot>1</indTot></prod><imposto><ICMS><ICMS20><orig>0</orig><CST>20</CST><modBC>3</modBC><pRedBC>61.1100</pRedBC><vBC>141.88</vBC><pICMS>18.0000</pICMS><vICMS>25.54</vICMS></ICMS20></ICMS><IPI><cEnq>999</cEnq><IPINT><CST>01</CST></IPINT></IPI><PIS><PISNT><CST>08</CST></PISNT></PIS><COFINS><COFINSNT><CST>08</CST></COFINSNT></COFINS></imposto><infAdProd>Reducao da base/Isencao ou nao sujeicao a IPI/RED. B.C CONF. ART 43 E ALIENA A1, ITEM 20 DO ANEXO IV DEC. 43080/02/PRAZO DE VALIDADE DE 10 (DEZ) DIAS, IMPRORROGAVEL, RE/PTA No 45.000012147-21 DF CONTAGEM/Relacao de Laudos e Lotes - Farinha Especial/210131 - L07 - MG5657 - 66931/TOTAL VFCP = R$ 0.00 E VFCPST = R$ 0.00 Codigo do CIOT: 125043719281/8309</infAdProd></det><det nItem="3"><prod><cProd>000000000000211082</cProd><cEAN>17896417203550</cEAN><xProd>MAS SEMOLA YARA NINHO N.3 20X500G</xProd><NCM>19021900</NCM><CEST>1704904</CEST><CFOP>5401</CFOP><uCom>FD</uCom><qCom>1.0000</qCom><vUnCom>50.9100000000</vUnCom><vProd>50.91</vProd><cEANTrib>7896417203553</cEANTrib><uTrib>UN</uTrib><qTrib>1.0000</qTrib><vUnTrib>50.9100000000</vUnTrib><indTot>1</indTot></prod><imposto><ICMS><ICMS70><orig>0</orig><CST>70</CST><modBC>3</modBC><pRedBC>33.3300</pRedBC><vBC>33.94</vBC><pICMS>18.0000</pICMS><vICMS>6.11</vICMS><modBCST>4</modBCST><pMVAST>35.0000</pMVAST><pRedBCST>61.1100</pRedBCST><vBCST>26.73</vBCST><pICMSST>18.0000</pICMSST><vICMSST>1.25</vICMSST></ICMS70></ICMS><IPI><cEnq>999</cEnq><IPINT><CST>01</CST></IPINT></IPI><PIS><PISNT><CST>08</CST></PISNT></PIS><COFINS><COFINSNT><CST>08</CST></COFINSNT></COFINS></imposto><infAdProd>Isencao ou nao sujeicao a IPI/Base reduzida para Sub.Trib./RED. B.C CONF. ART 43 E ALIENA A1, ITEM 20 DO ANEXO IV DEC. 43080/02/PRAZO DE VALIDADE DE 10 (DEZ) DIAS, IMPRORROGAVEL, RE/PTA No 45.000012147-21 DF CONTAGEM/TOTAL VFCP = R$ 0.00 E VFCPST = R$ 0.00 Codigo do CIOT: 125043719281/8309</infAdProd></det><det nItem="4"><prod><cProd>000000000000411108</cProd><cEAN>17896417204663</cEAN><xProd>MAS OVOS VILMA LASANHA CARTUCHO 20X500G</xProd><NCM>19021100</NCM><CEST>1704906</CEST><CFOP>5403</CFOP><uCom>CX</uCom><qCom>1.0000</qCom><vUnCom>128.2600000000</vUnCom><vProd>128.26</vProd><cEANTrib>7896417204666</cEANTrib><uTrib>UN</uTrib><qTrib>1.0000</qTrib><vUnTrib>128.2600000000</vUnTrib><indTot>1</indTot></prod><imposto><ICMS><ICMS70><orig>0</orig><CST>70</CST><modBC>3</modBC><pRedBC>61.1100</pRedBC><vBC>49.88</vBC><pICMS>18.0000</pICMS><vICMS>8.98</vICMS><modBCST>4</modBCST><pMVAST>35.0000</pMVAST><pRedBCST>61.1100</pRedBCST><vBCST>67.34</vBCST><pICMSST>18.0000</pICMSST><vICMSST>3.14</vICMSST></ICMS70></ICMS><IPI><cEnq>999</cEnq><IPINT><CST>01</CST></IPINT></IPI><PIS><PISNT><CST>08</CST></PISNT></PIS><COFINS><COFINSNT><CST>08</CST></COFINSNT></COFINS></imposto><infAdProd>Isencao ou nao sujeicao a IPI/Base reduzida para Sub.Trib./RED. B.C CONF. ART 43 E ALIENA A1, ITEM 20 DO ANEXO IV DEC. 43080/02/PRAZO DE VALIDADE DE 10 (DEZ) DIAS, IMPRORROGAVEL, RE/PTA No 45.000012147-21 DF CONTAGEM/TOTAL VFCP = R$ 0.00 E VFCPST = R$ 0.00 Codigo do CIOT: 125043719281/8309</infAdProd></det><det nItem="5"><prod><cProd>000000000000215390</cProd><cEAN>37896417202854</cEAN><xProd>MAS COMUM YARA ESP. No03 30X500g</xProd><NCM>19021900</NCM><CEST>1704903</CEST><CFOP>5401</CFOP><uCom>FD</uCom><qCom>1.0000</qCom><vUnCom>56.3500000000</vUnCom><vProd>56.35</vProd><cEANTrib>7896417202853</cEANTrib><uTrib>UN</uTrib><qTrib>1.0000</qTrib><vUnTrib>56.3500000000</vUnTrib><indTot>1</indTot></prod><imposto><ICMS><ICMS70><orig>0</orig><CST>70</CST><modBC>3</modBC><pRedBC>33.3300</pRedBC><vBC>37.57</vBC><pICMS>18.0000</pICMS><vICMS>6.76</vICMS><modBCST>4</modBCST><pMVAST>35.0000</pMVAST><pRedBCST>61.1100</pRedBCST><vBCST>29.58</vBCST><pICMSST>18.0000</pICMSST><vICMSST>1.38</vICMSST></ICMS70></ICMS><IPI><cEnq>999</cEnq><IPINT><CST>01</CST></IPINT></IPI><PIS><PISNT><CST>08</CST></PISNT></PIS><COFINS><COFINSNT><CST>08</CST></COFINSNT></COFINS></imposto><infAdProd>Isencao ou nao sujeicao a IPI/Base reduzida para Sub.Trib./RED. B.C CONF. ART 43 E ALIENA A1, ITEM 20 DO ANEXO IV DEC. 43080/02/PRAZO DE VALIDADE DE 10 (DEZ) DIAS, IMPRORROGAVEL, RE/PTA No 45.000012147-21 DF CONTAGEM/TOTAL VFCP = R$ 0.00 E VFCPST = R$ 0.00 Codigo do CIOT: 125043719281/8309</infAdProd></det><det nItem="6"><prod><cProd>000000000000210246</cProd><cEAN>17896417202027</cEAN><xProd>MAS COMUM YARA ESPAGUETE N.0 15X1KG</xProd><NCM>19021900</NCM><CEST>1704903</CEST><CFOP>5401</CFOP><uCom>FD</uCom><qCom>1.0000</qCom><vUnCom>56.3500000000</vUnCom><vProd>56.35</vProd><cEANTrib>7896417202020</cEANTrib><uTrib>UN</uTrib><qTrib>1.0000</qTrib><vUnTrib>56.3500000000</vUnTrib><indTot>1</indTot></prod><imposto><ICMS><ICMS70><orig>0</orig><CST>70</CST><modBC>3</modBC><pRedBC>33.3300</pRedBC><vBC>37.57</vBC><pICMS>18.0000</pICMS><vICMS>6.76</vICMS><modBCST>4</modBCST><pMVAST>35.0000</pMVAST><pRedBCST>61.1100</pRedBCST><vBCST>29.58</vBCST><pICMSST>18.0000</pICMSST><vICMSST>1.38</vICMSST></ICMS70></ICMS><IPI><cEnq>999</cEnq><IPINT><CST>01</CST></IPINT></IPI><PIS><PISNT><CST>08</CST></PISNT></PIS><COFINS><COFINSNT><CST>08</CST></COFINSNT></COFINS></imposto><infAdProd>Isencao ou nao sujeicao a IPI/Base reduzida para Sub.Trib./RED. B.C CONF. ART 43 E ALIENA A1, ITEM 20 DO ANEXO IV DEC. 43080/02/PRAZO DE VALIDADE DE 10 (DEZ) DIAS, IMPRORROGAVEL, RE/PTA No 45.000012147-21 DF CONTAGEM/TOTAL VFCP = R$ 0.00 E VFCPST = R$ 0.00 Codigo do CIOT: 125043719281/8309</infAdProd></det><det nItem="7"><prod><cProd>000000000000215168</cProd><cEAN>37896417223903</cEAN><xProd>MOLHO PIM.PICANTE 6X150 ML PIRATA PET</xProd><NCM>21039021</NCM><CEST>1703500</CEST><CFOP>5401</CFOP><uCom>SH</uCom><qCom>1.0000</qCom><vUnCom>18.6300000000</vUnCom><vProd>18.63</vProd><cEANTrib>7896417223902</cEANTrib><uTrib>UN</uTrib><qTrib>1.0000</qTrib><vUnTrib>18.6300000000</vUnTrib><indTot>1</indTot></prod><imposto><ICMS><ICMS10><orig>0</orig><CST>10</CST><modBC>3</modBC><vBC>18.63</vBC><pICMS>18.0000</pICMS><vICMS>3.35</vICMS><modBCST>4</modBCST><pMVAST>55.0000</pMVAST><vBCST>28.88</vBCST><pICMSST>18.0000</pICMSST><vICMSST>1.85</vICMSST></ICMS10></ICMS><IPI><cEnq>999</cEnq><IPINT><CST>01</CST></IPINT></IPI><PIS><PISAliq><CST>01</CST><vBC>18.63</vBC><pPIS>1.6500</pPIS><vPIS>0.31</vPIS></PISAliq></PIS><COFINS><COFINSAliq><CST>01</CST><vBC>18.63</vBC><pCOFINS>7.6000</pCOFINS><vCOFINS>1.42</vCOFINS></COFINSAliq></COFINS></imposto><infAdProd>Isencao ou nao sujeicao a IPI/Sujeito a ICMS e Sub.Trib./PRAZO DE VALIDADE DE 10 (DEZ) DIAS, IMPRORROGAVEL, RE/PTA No 45.000012147-21 DF CONTAGEM/TOTAL VFCP = R$ 0.00 E VFCPST = R$ 0.00 Codigo do CIOT: 125043719281/8309</infAdProd></det><det nItem="8"><prod><cProd>000000000000213017</cProd><cEAN>47896330511535</cEAN><xProd>FOLHA DE LOURO 30X6G PIRATA PCT</xProd><NCM>09109900</NCM><CFOP>5101</CFOP><uCom>PCT</uCom><qCom>1.0000</qCom><vUnCom>42.9400000000</vUnCom><vProd>42.94</vProd><cEANTrib>7896330511537</cEANTrib><uTrib>UN</uTrib><qTrib>1.0000</qTrib><vUnTrib>42.9400000000</vUnTrib><indTot>1</indTot></prod><imposto><ICMS><ICMS00><orig>0</orig><CST>00</CST><modBC>3</modBC><vBC>42.94</vBC><pICMS>12.0000</pICMS><vICMS>5.15</vICMS></ICMS00></ICMS><IPI><cEnq>999</cEnq><IPINT><CST>01</CST></IPINT></IPI><PIS><PISAliq><CST>01</CST><vBC>42.94</vBC><pPIS>1.6500</pPIS><vPIS>0.71</vPIS></PISAliq></PIS><COFINS><COFINSAliq><CST>01</CST><vBC>42.94</vBC><pCOFINS>7.6000</pCOFINS><vCOFINS>3.26</vCOFINS></COFINSAliq></COFINS></imposto><infAdProd>Isencao ou nao sujeicao a IPI/PRAZO DE VALIDADE DE 10 (DEZ) DIAS, IMPRORROGAVEL, RE/PTA No 45.000012147-21 DF CONTAGEM/DESTAQUE DO ICMS DE 12% CONFORME ART. 22 INCISO I DO REGIME ESPECIAL 45.000009035-40//TOTAL VFCP = R$ 0.00 E VFCPST = R$ 0.00 Codigo do CIOT: 125043719281/8309</infAdProd></det><total><ICMSTot><vBC>393.06</vBC><vICMS>68.17</vICMS><vICMSDeson>0.00</vICMSDeson><vFCP>0.00</vFCP><vBCST>182.11</vBCST><vST>9.00</vST><vFCPST>0.00</vFCPST><vFCPSTRet>0.00</vFCPSTRet><vProd>797.06</vProd><vFrete>0.00</vFrete><vSeg>0.00</vSeg><vDesc>0.00</vDesc><vII>0.00</vII><vIPI>0.00</vIPI><vIPIDevol>0.00</vIPIDevol><vPIS>1.02</vPIS><vCOFINS>4.68</vCOFINS><vOutro>0.00</vOutro><vNF>806.06</vNF></ICMSTot></total><transp><modFrete>0</modFrete><transporta><CPF>01255526610</CPF><xNome>CLEITON JUNIO VIEIRA MATIAS</xNome><xEnder>RUA DOS ESPANHOIS 5279</xEnder><xMun>CONTAGEM</xMun><UF>MG</UF></transporta><vol><qVol>18</qVol><esp>VOL</esp><pesoL>171.000</pesoL><pesoB>176.000</pesoB></vol></transp><cobr><fat><nFat>0903264728</nFat><vOrig>806.06</vOrig><vDesc>0.00</vDesc><vLiq>806.06</vLiq></fat><dup><nDup>001</nDup><dVenc>2021-08-31</dVenc><vDup>806.06</vDup></dup></cobr><pag><detPag><indPag>1</indPag><tPag>15</tPag><vPag>806.06</vPag></detPag></pag><infAdic><infCpl>FRETE: Valor Servico R$ 616,93 Base de calculo: R$ 616,93 Aliquota: 0,00% Valor de imposto Retido: R$0,00 TOTAL VFCP = R$ 0.00 E VFCPST = R$ 0.00</infCpl></infAdic></infNFe><Signature xmlns="http://www.w3.org/2000/09/xmldsig#"><SignedInfo><CanonicalizationMethod Algorithm="http://www.w3.org/TR/2001/REC-xml-c14n-20010315" /><SignatureMethod Algorithm="http://www.w3.org/2000/09/xmldsig#rsa-sha1" /><Reference URI="#NFe31210817159518000175550010033629631743766978"><Transforms><Transform Algorithm="http://www.w3.org/2000/09/xmldsig#enveloped-signature" /><Transform Algorithm="http://www.w3.org/TR/2001/REC-xml-c14n-20010315" /></Transforms><DigestMethod Algorithm="http://www.w3.org/2000/09/xmldsig#sha1" /><DigestValue>vNbO7iOoNRH/7fF+3FPn0h3YjO8=</DigestValue></Reference></SignedInfo><SignatureValue>DB7RcmUpLh1tU0f+cf973jcEc0OT893joKxZHOmFwxLAOP0BMhjaOCbQyqsPtzYkK943uxBIcyEJ
SuX+oXsEX4yG5syqZAThme2cDgsQf96VGhqexCY5nKQ7TroIxWqqpPzr2LHpF9UWUekVP0KiF1+o
Org1eUz9ii3JX2sHIV+30Oim8gdJWUnMXp4y3TRQ+z4JrsUpdfNemF9j0hHiHiMGXXokPbU2ovDV
ZGNHBFUJpd7GyR5UPf1WChyOakZIW0hL78G5wQ2HlWT50ZrS5qmZsM1KwNJ3Y/SV96KC2C84kbkS
K1HQ4b3LTHhboe/4txF2cmrD1GtXSkcMI1KIGw==</SignatureValue><KeyInfo><X509Data><X509Certificate>MIIIEzCCBfugAwIBAgIISDb4zhu+TiUwDQYJKoZIhvcNAQELBQAwdTELMAkGA1UEBhMCQlIxEzAR
BgNVBAoMCklDUC1CcmFzaWwxNjA0BgNVBAsMLVNlY3JldGFyaWEgZGEgUmVjZWl0YSBGZWRlcmFs
IGRvIEJyYXNpbCAtIFJGQjEZMBcGA1UEAwwQQUMgU0VSQVNBIFJGQiB2NTAeFw0yMDEyMDgxODAw
MDBaFw0yMTEyMDgxODAwMDBaMIIBODELMAkGA1UEBhMCQlIxCzAJBgNVBAgMAk1HMREwDwYDVQQH
DAhDT05UQUdFTTETMBEGA1UECgwKSUNQLUJyYXNpbDEYMBYGA1UECwwPMDAwMDAxMDA5ODg4ODk5
MTYwNAYDVQQLDC1TZWNyZXRhcmlhIGRhIFJlY2VpdGEgRmVkZXJhbCBkbyBCcmFzaWwgLSBSRkIx
FjAUBgNVBAsMDVJGQiBlLUNOUEogQTExGTAXBgNVBAsMEEFDIFNFUkFTQSBSRkIgdjUxFzAVBgNV
BAsMDjMyNDYwODYyMDAwMTkzMRMwEQYDVQQLDApQUkVTRU5DSUFMMUEwPwYDVQQDDDhET01JTkdP
UyBDT1NUQSBJTkRVU1RSSUFTIEFMSU1FTlRJQ0lBUyBTQToxNzE1OTUxODAwMDE3NTCCASIwDQYJ
KoZIhvcNAQEBBQADggEPADCCAQoCggEBAL3zpQJ46qQIZWlNtgme+qkQbXQHCn7GWowiqBUdZxYk
cZ89/NIbe0WNYxn9nxeECCtHqYD+Jaa3Uz1ongjf0ub7jFNR2CjYVf/gHzkpRQEwfZipQbknNZKw
ZCSaeMbL0suqSxtz8etIt5J4aC1TpKoLmYuaJ5Col86+f/d1ER/zteuG/4s1m+sW1KEH+ZB0U/QV
xIJsZYFQr+UuBwd9RTVYDi0DcJl2hsuQ6oS6rzTbytQfvWiaqLILzPBxy3tUNQqpHf46+ODOTRGB
F0KhE7i7Vwf+Fz3MqIG/n7pbImAPKzEj2lLYc2IR8p5Qk+DcnT3Ue6xkY51Zc3Bc3XUN6vkCAwEA
AaOCAuAwggLcMAkGA1UdEwQCMAAwHwYDVR0jBBgwFoAU7PFBUVeo5jrpXrOgIvkIirU6h48wgZkG
CCsGAQUFBwEBBIGMMIGJMEgGCCsGAQUFBzAChjxodHRwOi8vd3d3LmNlcnRpZmljYWRvZGlnaXRh
bC5jb20uYnIvY2FkZWlhcy9zZXJhc2FyZmJ2NS5wN2IwPQYIKwYBBQUHMAGGMWh0dHA6Ly9vY3Nw
LmNlcnRpZmljYWRvZGlnaXRhbC5jb20uYnIvc2VyYXNhcmZidjUwgbAGA1UdEQSBqDCBpYETRklT
Q0FMQFZJTE1BLkNPTS5CUqAgBgVgTAEDAqAXExVQQVRSSUNJQSBNQUNFRE8gQ09TVEGgGQYFYEwB
AwOgEBMOMTcxNTk1MTgwMDAxNzWgOAYFYEwBAwSgLxMtMTcwNjE5NzkwMTI1OTY4NTY2NzAwMDAw
MDAwMDAwMDAwMDAwMDAwMDAwMDAwoBcGBWBMAQMHoA4TDDAwMDAwMDAwMDAwMDBxBgNVHSAEajBo
MGYGBmBMAQIBDTBcMFoGCCsGAQUFBwIBFk5odHRwOi8vcHVibGljYWNhby5jZXJ0aWZpY2Fkb2Rp
Z2l0YWwuY29tLmJyL3JlcG9zaXRvcmlvL2RwYy9kZWNsYXJhY2FvLXJmYi5wZGYwHQYDVR0lBBYw
FAYIKwYBBQUHAwIGCCsGAQUFBwMEMIGdBgNVHR8EgZUwgZIwSqBIoEaGRGh0dHA6Ly93d3cuY2Vy
dGlmaWNhZG9kaWdpdGFsLmNvbS5ici9yZXBvc2l0b3Jpby9sY3Ivc2VyYXNhcmZidjUuY3JsMESg
QqBAhj5odHRwOi8vbGNyLmNlcnRpZmljYWRvcy5jb20uYnIvcmVwb3NpdG9yaW8vbGNyL3NlcmFz
YXJmYnY1LmNybDAdBgNVHQ4EFgQUIec19BAAZVpRICSicBxUUxvYdyYwDgYDVR0PAQH/BAQDAgXg
MA0GCSqGSIb3DQEBCwUAA4ICAQBjThd1gBy2cq7FIkK7G4RZqNUa2GDynCwNfUnW5C0WzF88EPtK
B0OtMQ3dCeBq3zd64P4YzvVtQOWAy9nFTZpnICUKpEg+7qw1feZIzqwrSvqLPcYoCwXgqFHxLb+V
Kgng14riydF3QZyb5UzE+1DsBsL2KpAza7dlFD83BWo08QMeFxt/UPuvmk7e3Re4h0C+ZspMEr4h
7t2bEc7AcY7PyYJdraR7nBcrkxZ9NWFf8bnbUryPkjPNhA/x+9bxfvUKcA0ct3gkjePgBXrjWdp4
7ZB3i4gyE4k99UBVAwF+TSE1IWS9yCh2/mVLbGVKXBSwwqsiencEbYVcGll3xg9kBqD295Xp5j2U
FdBoCowb8EnYZKwguTA2cWupW2f+mXXJ8zUU/d0E79HHukR5aO3sTNBOsBvzMLKH86raGdUKC/Bh
Ebd+52xR7yyo1wxJxSmmXZ5xOj24Ol4Nv84youaBrwTr5qXWX8mrf3u1ngqpvJP0VvoGlwJScmNi
t30RNx5jdK6hB31X0Rfrwpz4zn7UtHeT0Mp32IuDDYuOhFO5cyE+QJf0qG6hjM5Jy62MEfu/GK65
kCnUwI7rZki15yhJeSozdvwUspvegzuLIn7HIPq48mHcC0hTx2aT1B+KYVj2+1dgTLpAy0EP4haU
yFEnLUYl70MVxHtCG7xrsJ1CvA==</X509Certificate></X509Data></KeyInfo></Signature></NFe><protNFe versao="4.00"><infProt Id="ID131214275366230">
  <tpAmb>1</tpAmb>
  <verAplic>14.4.26-AC1</verAplic>
  <chNFe>31210817159518000175550010033629631743766978</chNFe>
  <dhRecbto>2021-08-03T04:50:13-03:00</dhRecbto>
  <nProt>131214275366230</nProt>
  <digVal>vNbO7iOoNRH/7fF+3FPn0h3YjO8=</digVal>
  <cStat>100</cStat>
  <xMotivo>Autorizado o uso da NF-e</xMotivo>
</infProt></protNFe></nfeProc>