<?xml version="1.0" encoding="UTF-8"?><nfeProc versao="4.00" xmlns="http://www.portalfiscal.inf.br/nfe"><NFe xmlns="http://www.portalfiscal.inf.br/nfe"><infNFe versao="4.00" Id="NFe31190123797376000174550000037897971383138961"><ide><cUF>31</cUF><cNF>38313896</cNF><natOp>Venda</natOp><mod>55</mod><serie>0</serie><nNF>3789797</nNF><dhEmi>2019-01-28T09:26:49-02:00</dhEmi><dhSaiEnt>2019-01-28T09:26:49-02:00</dhSaiEnt><tpNF>1</tpNF><idDest>1</idDest><cMunFG>3152105</cMunFG><tpImp>1</tpImp><tpEmis>1</tpEmis><cDV>1</cDV><tpAmb>1</tpAmb><finNFe>1</finNFe><indFinal>0</indFinal><indPres>0</indPres><procEmi>0</procEmi><verProc>NDDigital NFe 4.7.3</verProc></ide><emit><CNPJ>23797376000174</CNPJ><xNome>BCR COMERCIO E INDUSTRIA SA</xNome><xFant>BCR PONTE NOVA-MG</xFant><enderEmit><xLgr>ROD MG 329 -TREVO ORATORIOS - KM</xLgr><nro>008</nro><xBairro>ANA FLORENCIA</xBairro><cMun>3152105</cMun><xMun>PONTE NOVA</xMun><UF>MG</UF><CEP>35432900</CEP><cPais>1058</cPais><xPais>BRASIL</xPais><fone>3138192000</fone></enderEmit><IE>5210278810023</IE><IM>74004937</IM><CNAE>4693100</CNAE><CRT>3</CRT></emit><dest><CNPJ>42853549000179</CNPJ><xNome>COMERCIAL SANTA MATILDE LTDA - 20722</xNome><enderDest><xLgr>AV SANTA MATILDE</xLgr><nro>910</nro><xCpl>LJ 02</xCpl><xBairro>SANTA MATILDE</xBairro><cMun>3118304</cMun><xMun>CONSELHEIRO LAFAIETE</xMun><UF>MG</UF><CEP>36400000</CEP><cPais>1058</cPais><xPais>BRASIL</xPais><fone>3137623660</fone></enderDest><indIEDest>1</indIEDest><IE>1838080270069</IE><email>casadaracaosm@hotmail.com</email></dest><det nItem="1"><prod><cProd>92713</cProd><cEAN>7898319083028</cEAN><xProd>LONA AGRO PTA/BCA 6X100M 72KG LONAX</xProd><NCM>39202019</NCM><CEST>1400400</CEST><indEscala>S</indEscala><CFOP>5403</CFOP><uCom>RL1</uCom><qCom>1.0000</qCom><vUnCom>558.6600000000</vUnCom><vProd>558.66</vProd><cEANTrib>7898319083028</cEANTrib><uTrib>RL1</uTrib><qTrib>1.0000</qTrib><vUnTrib>558.6600000000</vUnTrib><indTot>1</indTot><nItemPed>10</nItemPed></prod><imposto><ICMS><ICMS70><orig>0</orig><CST>70</CST><modBC>3</modBC><pRedBC>0.0000</pRedBC><vBC>442.80</vBC><pICMS>12.0000</pICMS><vICMS>53.14</vICMS><modBCST>4</modBCST><pMVAST>28.0000</pMVAST><vBCST>566.78</vBCST><pICMSST>18.0000</pICMSST><vICMSST>48.88</vICMSST></ICMS70></ICMS><PIS><PISAliq><CST>01</CST><vBC>558.66</vBC><pPIS>1.6500</pPIS><vPIS>9.22</vPIS></PISAliq></PIS><COFINS><COFINSAliq><CST>01</CST><vBC>558.66</vBC><pCOFINS>7.6000</pCOFINS><vCOFINS>42.46</vCOFINS></COFINSAliq></COFINS></imposto></det><det nItem="2"><prod><cProd>3966</cProd><cEAN>7898100550524</cEAN><xProd>PENEIRA AREIA 55 SAO JORGE</xProd><NCM>96040000</NCM><CFOP>5102</CFOP><uCom>AM6</uCom><qCom>1.0000</qCom><vUnCom>62.9600000000</vUnCom><vProd>62.96</vProd><cEANTrib>7898100550869</cEANTrib><uTrib>AM6</uTrib><qTrib>1.0000</qTrib><vUnTrib>62.9600000000</vUnTrib><indTot>1</indTot><nItemPed>14</nItemPed></prod><imposto><ICMS><ICMS00><orig>0</orig><CST>00</CST><modBC>3</modBC><vBC>62.96</vBC><pICMS>18.0000</pICMS><vICMS>11.33</vICMS></ICMS00></ICMS><PIS><PISAliq><CST>01</CST><vBC>62.96</vBC><pPIS>1.6500</pPIS><vPIS>1.04</vPIS></PISAliq></PIS><COFINS><COFINSAliq><CST>01</CST><vBC>62.96</vBC><pCOFINS>7.6000</pCOFINS><vCOFINS>4.78</vCOFINS></COFINSAliq></COFINS></imposto></det><det nItem="3"><prod><cProd>3972</cProd><cEAN>7898100550449</cEAN><xProd>PENEIRA CAFE/CHAPISCO 55 SAO JORGE</xProd><NCM>96040000</NCM><CFOP>5102</CFOP><uCom>AM6</uCom><qCom>1.0000</qCom><vUnCom>62.9600000000</vUnCom><vProd>62.96</vProd><cEANTrib>7898100550142</cEANTrib><uTrib>AM6</uTrib><qTrib>1.0000</qTrib><vUnTrib>62.9600000000</vUnTrib><indTot>1</indTot><nItemPed>15</nItemPed></prod><imposto><ICMS><ICMS00><orig>0</orig><CST>00</CST><modBC>3</modBC><vBC>62.96</vBC><pICMS>18.0000</pICMS><vICMS>11.33</vICMS></ICMS00></ICMS><PIS><PISAliq><CST>01</CST><vBC>62.96</vBC><pPIS>1.6500</pPIS><vPIS>1.04</vPIS></PISAliq></PIS><COFINS><COFINSAliq><CST>01</CST><vBC>62.96</vBC><pCOFINS>7.6000</pCOFINS><vCOFINS>4.78</vCOFINS></COFINSAliq></COFINS></imposto></det><det nItem="4"><prod><cProd>3979</cProd><cEAN>7898100550418</cEAN><xProd>PENEIRA FEIJAO/CHAPISCO 55 SAO JORGE</xProd><NCM>96040000</NCM><CFOP>5102</CFOP><uCom>AM6</uCom><qCom>1.0000</qCom><vUnCom>62.9600000000</vUnCom><vProd>62.96</vProd><cEANTrib>7898100550111</cEANTrib><uTrib>AM6</uTrib><qTrib>1.0000</qTrib><vUnTrib>62.9600000000</vUnTrib><indTot>1</indTot><nItemPed>16</nItemPed></prod><imposto><ICMS><ICMS00><orig>0</orig><CST>00</CST><modBC>3</modBC><vBC>62.96</vBC><pICMS>18.0000</pICMS><vICMS>11.33</vICMS></ICMS00></ICMS><PIS><PISAliq><CST>01</CST><vBC>62.96</vBC><pPIS>1.6500</pPIS><vPIS>1.04</vPIS></PISAliq></PIS><COFINS><COFINSAliq><CST>01</CST><vBC>62.96</vBC><pCOFINS>7.6000</pCOFINS><vCOFINS>4.78</vCOFINS></COFINSAliq></COFINS></imposto></det><det nItem="5"><prod><cProd>93106</cProd><cEAN>7892775021129</cEAN><xProd>CRAVO OMEGA E-5</xProd><NCM>73170090</NCM><CEST>1005700</CEST><indEscala>S</indEscala><CFOP>5403</CFOP><uCom>CX250</uCom><qCom>1.0000</qCom><vUnCom>53.4900000000</vUnCom><vProd>53.49</vProd><cEANTrib>7892775021129</cEANTrib><uTrib>CX250</uTrib><qTrib>1.0000</qTrib><vUnTrib>53.4900000000</vUnTrib><indTot>1</indTot><nItemPed>11</nItemPed></prod><imposto><ICMS><ICMS70><orig>2</orig><CST>70</CST><modBC>3</modBC><pRedBC>0.0000</pRedBC><vBC>37.50</vBC><pICMS>4.0000</pICMS><vICMS>1.50</vICMS><modBCST>4</modBCST><pMVAST>69.7600</pMVAST><vBCST>63.66</vBCST><pICMSST>18.0000</pICMSST><vICMSST>9.96</vICMSST></ICMS70></ICMS><PIS><PISAliq><CST>01</CST><vBC>53.49</vBC><pPIS>1.6500</pPIS><vPIS>0.88</vPIS></PISAliq></PIS><COFINS><COFINSAliq><CST>01</CST><vBC>53.49</vBC><pCOFINS>7.6000</pCOFINS><vCOFINS>4.07</vCOFINS></COFINSAliq></COFINS></imposto></det><det nItem="6"><prod><cProd>98679</cProd><cEAN>7898189860316</cEAN><xProd>DESMAMADOR DE BEZERRO INJESUL</xProd><NCM>39269090</NCM><CFOP>5102</CFOP><uCom>PT12</uCom><qCom>1.0000</qCom><vUnCom>8.4100000000</vUnCom><vProd>8.41</vProd><cEANTrib>7898189860231</cEANTrib><uTrib>PT12</uTrib><qTrib>1.0000</qTrib><vUnTrib>8.4100000000</vUnTrib><indTot>1</indTot><nItemPed>12</nItemPed></prod><imposto><ICMS><ICMS00><orig>0</orig><CST>00</CST><modBC>3</modBC><vBC>8.41</vBC><pICMS>18.0000</pICMS><vICMS>1.51</vICMS></ICMS00></ICMS><PIS><PISAliq><CST>01</CST><vBC>8.41</vBC><pPIS>1.6500</pPIS><vPIS>0.14</vPIS></PISAliq></PIS><COFINS><COFINSAliq><CST>01</CST><vBC>8.41</vBC><pCOFINS>7.6000</pCOFINS><vCOFINS>0.64</vCOFINS></COFINSAliq></COFINS></imposto></det><det nItem="7"><prod><cProd>2046</cProd><cEAN>17898031530074</cEAN><xProd>VELA P/ FILTRO CARVAO ATIVADO ELITE</xProd><NCM>69120000</NCM><CEST>1401000</CEST><indEscala>S</indEscala><CFOP>5403</CFOP><uCom>CX12</uCom><qCom>1.0000</qCom><vUnCom>50.9600000000</vUnCom><vProd>50.96</vProd><cEANTrib>7898031530077</cEANTrib><uTrib>CX12</uTrib><qTrib>1.0000</qTrib><vUnTrib>50.9600000000</vUnTrib><indTot>1</indTot><nItemPed>5</nItemPed></prod><imposto><ICMS><ICMS70><orig>0</orig><CST>70</CST><modBC>3</modBC><pRedBC>0.0000</pRedBC><vBC>36.48</vBC><pICMS>12.0000</pICMS><vICMS>4.38</vICMS><modBCST>4</modBCST><pMVAST>82.4400</pMVAST><vBCST>66.55</vBCST><pICMSST>18.0000</pICMSST><vICMSST>7.60</vICMSST></ICMS70></ICMS><PIS><PISAliq><CST>01</CST><vBC>50.96</vBC><pPIS>1.6500</pPIS><vPIS>0.84</vPIS></PISAliq></PIS><COFINS><COFINSAliq><CST>01</CST><vBC>50.96</vBC><pCOFINS>7.6000</pCOFINS><vCOFINS>3.87</vCOFINS></COFINSAliq></COFINS></imposto></det><det nItem="8"><prod><cProd>11944</cProd><cEAN>27896367720029</cEAN><xProd>VASSOURA GRAMA C/CB 22 PALETAS METAL FAMASTIL - REF 00602.001</xProd><NCM>82013000</NCM><CEST>0800400</CEST><indEscala>S</indEscala><CFOP>5403</CFOP><uCom>AM6</uCom><qCom>1.0000</qCom><vUnCom>73.3700000000</vUnCom><vProd>73.37</vProd><cEANTrib>7896367720025</cEANTrib><uTrib>AM6</uTrib><qTrib>1.0000</qTrib><vUnTrib>73.3700000000</vUnTrib><indTot>1</indTot><nItemPed>3</nItemPed><nFCI>4DD71996-D2A2-4348-80CD-EECCF9D74BE9</nFCI></prod><imposto><ICMS><ICMS70><orig>5</orig><CST>70</CST><modBC>3</modBC><pRedBC>0.0000</pRedBC><vBC>54.24</vBC><pICMS>12.0000</pICMS><vICMS>6.51</vICMS><modBCST>4</modBCST><pMVAST>55.6100</pMVAST><vBCST>84.40</vBCST><pICMSST>18.0000</pICMSST><vICMSST>8.68</vICMSST></ICMS70></ICMS><PIS><PISAliq><CST>01</CST><vBC>73.37</vBC><pPIS>1.6500</pPIS><vPIS>1.21</vPIS></PISAliq></PIS><COFINS><COFINSAliq><CST>01</CST><vBC>73.37</vBC><pCOFINS>7.6000</pCOFINS><vCOFINS>5.58</vCOFINS></COFINSAliq></COFINS></imposto></det><det nItem="9"><prod><cProd>5881</cProd><cEAN>7898049716425</cEAN><xProd>ADE INJETAVEL 050ML ZOETIS(E)</xProd><NCM>30045090</NCM><CFOP>5102</CFOP><uCom>UN1</uCom><qCom>2.0000</qCom><vUnCom>23.8800000000</vUnCom><vProd>47.76</vProd><cEANTrib>7898049716425</cEANTrib><uTrib>UN1</uTrib><qTrib>2.0000</qTrib><vUnTrib>23.8800000000</vUnTrib><indTot>1</indTot><nItemPed>8</nItemPed><nFCI>5BA0D2AD-C660-4EE6-A58A-C451CE232B9A</nFCI><rastro><nLote>001/18</nLote><qLote>2.000</qLote><dFab>2019-01-04</dFab><dVal>2020-11-30</dVal></rastro></prod><imposto><ICMS><ICMS40><orig>5</orig><CST>40</CST></ICMS40></ICMS><PIS><PISNT><CST>04</CST></PISNT></PIS><COFINS><COFINSNT><CST>04</CST></COFINSNT></COFINS></imposto></det><det nItem="10"><prod><cProd>111334</cProd><cEAN>7898904869877</cEAN><xProd>COLA INSTANTANEA 725 20GR TEKBOND(E)</xProd><NCM>35061010</NCM><CFOP>5102</CFOP><uCom>UN1</uCom><qCom>10.0000</qCom><vUnCom>5.0200000000</vUnCom><vProd>50.20</vProd><cEANTrib>7898904869877</cEANTrib><uTrib>UN1</uTrib><qTrib>10.0000</qTrib><vUnTrib>5.0200000000</vUnTrib><indTot>1</indTot><nItemPed>2</nItemPed></prod><imposto><ICMS><ICMS00><orig>2</orig><CST>00</CST><modBC>3</modBC><vBC>50.20</vBC><pICMS>18.0000</pICMS><vICMS>9.04</vICMS></ICMS00></ICMS><PIS><PISAliq><CST>01</CST><vBC>50.20</vBC><pPIS>1.6500</pPIS><vPIS>0.83</vPIS></PISAliq></PIS><COFINS><COFINSAliq><CST>01</CST><vBC>50.20</vBC><pCOFINS>7.6000</pCOFINS><vCOFINS>3.82</vCOFINS></COFINSAliq></COFINS></imposto></det><det nItem="11"><prod><cProd>81888</cProd><cEAN>7898364910089</cEAN><xProd>COLEIRA ANTI-PULGA/CARRAP 16G CAES GATOS PET(E)</xProd><NCM>38089999</NCM><CFOP>5102</CFOP><uCom>UN1</uCom><qCom>6.0000</qCom><vUnCom>11.7700000000</vUnCom><vProd>70.62</vProd><cEANTrib>7898364910089</cEANTrib><uTrib>UN1</uTrib><qTrib>6.0000</qTrib><vUnTrib>11.7700000000</vUnTrib><indTot>1</indTot><nItemPed>9</nItemPed></prod><imposto><ICMS><ICMS00><orig>0</orig><CST>00</CST><modBC>3</modBC><vBC>70.62</vBC><pICMS>18.0000</pICMS><vICMS>12.71</vICMS></ICMS00></ICMS><PIS><PISAliq><CST>01</CST><vBC>70.62</vBC><pPIS>1.6500</pPIS><vPIS>1.17</vPIS></PISAliq></PIS><COFINS><COFINSAliq><CST>01</CST><vBC>70.62</vBC><pCOFINS>7.6000</pCOFINS><vCOFINS>5.37</vCOFINS></COFINSAliq></COFINS></imposto></det><det nItem="12"><prod><cProd>43027</cProd><cEAN>SEM GTIN</cEAN><xProd>LIMATAO MOTOSSERRA KF N 8X3/16(E)</xProd><NCM>82031010</NCM><CEST>0800800</CEST><indEscala>S</indEscala><CFOP>5403</CFOP><uCom>CX12</uCom><qCom>1.0000</qCom><vUnCom>37.7400000000</vUnCom><vProd>37.74</vProd><cEANTrib>SEM GTIN</cEANTrib><uTrib>CX12</uTrib><qTrib>1.0000</qTrib><vUnTrib>37.7400000000</vUnTrib><indTot>1</indTot><nItemPed>7</nItemPed></prod><imposto><ICMS><ICMS70><orig>0</orig><CST>70</CST><modBC>3</modBC><pRedBC>0.0000</pRedBC><vBC>25.80</vBC><pICMS>12.0000</pICMS><vICMS>3.10</vICMS><modBCST>4</modBCST><pMVAST>55.6100</pMVAST><vBCST>40.15</vBCST><pICMSST>18.0000</pICMSST><vICMSST>4.13</vICMSST></ICMS70></ICMS><PIS><PISAliq><CST>01</CST><vBC>37.74</vBC><pPIS>1.6500</pPIS><vPIS>0.62</vPIS></PISAliq></PIS><COFINS><COFINSAliq><CST>01</CST><vBC>37.74</vBC><pCOFINS>7.6000</pCOFINS><vCOFINS>2.87</vCOFINS></COFINSAliq></COFINS></imposto></det><det nItem="13"><prod><cProd>36647</cProd><cEAN>17891645068940</cEAN><xProd>LIMATAO MOTOSSERRA KF N 8X7/32(E)</xProd><NCM>82031010</NCM><CEST>0800800</CEST><indEscala>S</indEscala><CFOP>5403</CFOP><uCom>CX12</uCom><qCom>1.0000</qCom><vUnCom>37.7400000000</vUnCom><vProd>37.74</vProd><cEANTrib>17891645068940</cEANTrib><uTrib>CX12</uTrib><qTrib>1.0000</qTrib><vUnTrib>37.7400000000</vUnTrib><indTot>1</indTot><nItemPed>6</nItemPed></prod><imposto><ICMS><ICMS70><orig>0</orig><CST>70</CST><modBC>3</modBC><pRedBC>0.0000</pRedBC><vBC>28.08</vBC><pICMS>12.0000</pICMS><vICMS>3.37</vICMS><modBCST>4</modBCST><pMVAST>55.6100</pMVAST><vBCST>43.70</vBCST><pICMSST>18.0000</pICMSST><vICMSST>4.50</vICMSST></ICMS70></ICMS><PIS><PISAliq><CST>01</CST><vBC>37.74</vBC><pPIS>1.6500</pPIS><vPIS>0.62</vPIS></PISAliq></PIS><COFINS><COFINSAliq><CST>01</CST><vBC>37.74</vBC><pCOFINS>7.6000</pCOFINS><vCOFINS>2.87</vCOFINS></COFINSAliq></COFINS></imposto></det><det nItem="14"><prod><cProd>14268</cProd><cEAN>7896014900107</cEAN><xProd>PULMODRAZIN REFORCADO 10ML PEARSON(E)</xProd><NCM>30041020</NCM><CFOP>5102</CFOP><uCom>UN1</uCom><qCom>2.0000</qCom><vUnCom>12.6100000000</vUnCom><vProd>25.22</vProd><cEANTrib>7896014900107</cEANTrib><uTrib>UN1</uTrib><qTrib>2.0000</qTrib><vUnTrib>12.6100000000</vUnTrib><indTot>1</indTot><nItemPed>4</nItemPed><nFCI>8C350C26-8048-4488-9FF6-37FF11C9EBD5</nFCI><rastro><nLote>004/18B</nLote><qLote>2.000</qLote><dFab>2018-11-03</dFab><dVal>2021-07-01</dVal></rastro></prod><imposto><ICMS><ICMS40><orig>5</orig><CST>40</CST></ICMS40></ICMS><PIS><PISNT><CST>04</CST></PISNT></PIS><COFINS><COFINSNT><CST>04</CST></COFINSNT></COFINS></imposto></det><det nItem="15"><prod><cProd>66087</cProd><cEAN>SEM GTIN</cEAN><xProd>CARRINHO DE MAO PNEU CAM 45L 3,25X8 VML MAESTRO - REF REF 02353</xProd><NCM>87168000</NCM><CFOP>5102</CFOP><uCom>UN1</uCom><qCom>2.0000</qCom><vUnCom>77.5600000000</vUnCom><vProd>155.12</vProd><cEANTrib>SEM GTIN</cEANTrib><uTrib>UN1</uTrib><qTrib>2.0000</qTrib><vUnTrib>77.5600000000</vUnTrib><indTot>1</indTot><nItemPed>17</nItemPed><nFCI>F226A706-8BF1-46F9-9053-9CC98547FF9E</nFCI></prod><imposto><ICMS><ICMS00><orig>5</orig><CST>00</CST><modBC>3</modBC><vBC>155.12</vBC><pICMS>18.0000</pICMS><vICMS>27.92</vICMS></ICMS00></ICMS><PIS><PISAliq><CST>01</CST><vBC>155.12</vBC><pPIS>1.6500</pPIS><vPIS>2.56</vPIS></PISAliq></PIS><COFINS><COFINSAliq><CST>01</CST><vBC>155.12</vBC><pCOFINS>7.6000</pCOFINS><vCOFINS>11.79</vCOFINS></COFINSAliq></COFINS></imposto></det><det nItem="16"><prod><cProd>110604</cProd><cEAN>7908949044716</cEAN><xProd>*TINTA SPRAY ECO BCR ALUM ALTA TEMP 400ML - REF 46200</xProd><NCM>32082011</NCM><CEST>2400100</CEST><indEscala>S</indEscala><CFOP>5403</CFOP><uCom>CX6</uCom><qCom>1.0000</qCom><vUnCom>41.8800000000</vUnCom><vProd>41.88</vProd><cEANTrib>7908949044716</cEANTrib><uTrib>CX6</uTrib><qTrib>1.0000</qTrib><vUnTrib>41.8800000000</vUnTrib><indTot>1</indTot><nItemPed>1</nItemPed></prod><imposto><ICMS><ICMS70><orig>0</orig><CST>70</CST><modBC>3</modBC><pRedBC>0.0000</pRedBC><vBC>31.02</vBC><pICMS>12.0000</pICMS><vICMS>3.72</vICMS><modBCST>4</modBCST><pMVAST>76.0000</pMVAST><vBCST>54.60</vBCST><pICMSST>18.0000</pICMSST><vICMSST>6.11</vICMSST></ICMS70></ICMS><PIS><PISAliq><CST>01</CST><vBC>41.88</vBC><pPIS>1.6500</pPIS><vPIS>0.69</vPIS></PISAliq></PIS><COFINS><COFINSAliq><CST>01</CST><vBC>41.88</vBC><pCOFINS>7.6000</pCOFINS><vCOFINS>3.18</vCOFINS></COFINSAliq></COFINS></imposto></det><det nItem="17"><prod><cProd>110603</cProd><cEAN>7908949044723</cEAN><xProd>*TINTA SPRAY ECO BCR PTO FOSCO ALTA TEMP 400ML - REF 46201</xProd><NCM>32082011</NCM><CEST>2400100</CEST><indEscala>S</indEscala><CFOP>5403</CFOP><uCom>CX6</uCom><qCom>1.0000</qCom><vUnCom>41.8800000000</vUnCom><vProd>41.88</vProd><cEANTrib>7908949044723</cEANTrib><uTrib>CX6</uTrib><qTrib>1.0000</qTrib><vUnTrib>41.8800000000</vUnTrib><indTot>1</indTot><nItemPed>13</nItemPed></prod><imposto><ICMS><ICMS70><orig>0</orig><CST>70</CST><modBC>3</modBC><pRedBC>0.0000</pRedBC><vBC>31.02</vBC><pICMS>12.0000</pICMS><vICMS>3.72</vICMS><modBCST>4</modBCST><pMVAST>76.0000</pMVAST><vBCST>54.60</vBCST><pICMSST>18.0000</pICMSST><vICMSST>6.11</vICMSST></ICMS70></ICMS><PIS><PISAliq><CST>01</CST><vBC>41.88</vBC><pPIS>1.6500</pPIS><vPIS>0.69</vPIS></PISAliq></PIS><COFINS><COFINSAliq><CST>01</CST><vBC>41.88</vBC><pCOFINS>7.6000</pCOFINS><vCOFINS>3.18</vCOFINS></COFINSAliq></COFINS></imposto></det><total><ICMSTot><vBC>1160.17</vBC><vICMS>164.61</vICMS><vICMSDeson>0.00</vICMSDeson><vFCP>0.00</vFCP><vBCST>974.44</vBCST><vST>95.97</vST><vFCPST>0.00</vFCPST><vFCPSTRet>0.00</vFCPSTRet><vProd>1441.93</vProd><vFrete>0.00</vFrete><vSeg>0.00</vSeg><vDesc>0.00</vDesc><vII>0.00</vII><vIPI>0.00</vIPI><vIPIDevol>0.00</vIPIDevol><vPIS>22.59</vPIS><vCOFINS>104.04</vCOFINS><vOutro>0.00</vOutro><vNF>1537.90</vNF></ICMSTot></total><transp><modFrete>0</modFrete><transporta><CPF>28001761649</CPF><xNome>FRANCISCO NOGUEIRA FLORESTA - 104741</xNome><IE>ISENTO</IE><xEnder>RUA SANTA EFIGENIA 185</xEnder><xMun>URUCANIA</xMun><UF>MG</UF></transporta><vol><qVol>16</qVol><pesoL>112.080</pesoL><pesoB>112.080</pesoB></vol></transp><cobr><fat><nFat>3789797</nFat><vOrig>1537.90</vOrig><vLiq>1537.90</vLiq></fat><dup><nDup>001</nDup><dVenc>2019-02-24</dVenc><vDup>307.58</vDup></dup><dup><nDup>002</nDup><dVenc>2019-03-16</dVenc><vDup>307.58</vDup></dup><dup><nDup>003</nDup><dVenc>2019-04-05</dVenc><vDup>307.58</vDup></dup><dup><nDup>004</nDup><dVenc>2019-04-25</dVenc><vDup>307.58</vDup></dup><dup><nDup>005</nDup><dVenc>2019-05-15</dVenc><vDup>307.58</vDup></dup></cobr><pag><detPag><tPag>15</tPag><vPag>1537.90</vPag></detPag></pag><infAdic><infCpl>ICMS RET CONV 100/97 ICMS RET.CONV.74/94 REGIME ESPECIAL. e-PTA 45.000010242-30 - DESTAQUE ST CONF. ANEXO XV RICMS/MG - NroCarga: 313098 *Itens Emergenciais: AEROSSOIS - 2.1 - ONU 1950 - GASES INFLAMAVEIS - ( VOLUME: 3+2+4+7 = 16 ) ATENCAO - PRAZO DE VALIDADE DE 8(OITO) DIAS, IMPRORROGAVEL REG. ESP. DLT / SER No. 01.084.0865-1 PTA No. 45.000001779-54 / GARANTIA - CERTIFICAMOS QUE OS PRODUTOS ESTAO ADEQUADAMENTE EMBALADOS PARA SUPORTAREM RISCOS NORMAIS DE CARREGAMENTO, TRANSPORTE E DESCARGA, CONFORME DECRETO No. 96044/88 / CALCULO DO ICMS NA PRESTACAO DE SERVICO DE TRANSPORTE DE CARGAS NOS TERMOS DO ANEXO XV-CAP.II SECAO I ART. 4 RICMS/MG-02</infCpl></infAdic></infNFe><Signature xmlns="http://www.w3.org/2000/09/xmldsig#"><SignedInfo><CanonicalizationMethod Algorithm="http://www.w3.org/TR/2001/REC-xml-c14n-20010315" /><SignatureMethod Algorithm="http://www.w3.org/2000/09/xmldsig#rsa-sha1" /><Reference URI="#NFe31190123797376000174550000037897971383138961"><Transforms><Transform Algorithm="http://www.w3.org/2000/09/xmldsig#enveloped-signature" /><Transform Algorithm="http://www.w3.org/TR/2001/REC-xml-c14n-20010315" /></Transforms><DigestMethod Algorithm="http://www.w3.org/2000/09/xmldsig#sha1" /><DigestValue>6JJrStroA3+e8Qb7NMqK95osiH8=</DigestValue></Reference></SignedInfo><SignatureValue>0XvQqAHLTTURb9QFQgvfO/p1S2cGa4zlHCcozr0iNQGTnT7eSmfVKLXbiNeYFdu6hdpy2FPSIwnm+ChmVqJriJHiyZMnuDCImBjF8xbHlLALA6cIqkLs6M7FNRcswFddM/l7aW/eViGrw+X6J4mZs31h5ikAIAqgr2Amx/H4aL0=</SignatureValue><KeyInfo><X509Data><X509Certificate>MIICOTCCAaKgAwIBAgIQJpLn3fwH17RNXJHw5VenaDANBgkqhkiG9w0BAQUFADBbMVkwVwYDVQQDHlAAdwB3AHcALgBmAHMAaQBzAHQALgBjAG8AbQAuAGIAcgAgACgAUwBFAE0AIABWAEEATABJAEQAQQBEAEUAIABKAFUAUgDNAEQASQBDAEEAKTAeFw0xNTEyMjQwODI1MjVaFw0xODEyMjQwODI1MjVaMFsxWTBXBgNVBAMeUAB3AHcAdwAuAGYAcwBpAHMAdAAuAGMAbwBtAC4AYgByACAAKABTAEUATQAgAFYAQQBMAEkARABBAEQARQAgAEoAVQBSAM0ARABJAEMAQQApMIGfMA0GCSqGSIb3DQEBAQUAA4GNADCBiQKBgQDX4BYmJiNwrPz9At2ioXYkMuMWAOf669VPS3SAzIKkJLhSE7Bf9sbTjGHRFZhs6STxKkMBKKnx6dqAEMGlQwDSU42/kqhGya28SUn3HigH2w3dR/536Gt4eAxyLp9ODNXUqWTpnraWCeT41kcnJ27cmOAUMxzxDcsA93n32L4u8wIDAQABMA0GCSqGSIb3DQEBBQUAA4GBAAN89zf+wSFL+4+2Ic8mGva8Z51EzYzNgYEqXwEMHxw4jCxxbsuxewQWedSGWi3SFZla6zmNUEA+UO95tSZ353klTvWDzut2BFSJOPLcMu8HPTTdnMt4ofVeVqKyi2vp+3t78vjqDAAfSAu5C9wT7stoUx41Nok+L6WbmpOIgvHy</X509Certificate></X509Data></KeyInfo></Signature></NFe><protNFe versao="4.00"><infProt><tpAmb>1</tpAmb><verAplic>NDDigital NFe 4.7.3</verAplic><chNFe>31190123797376000174550000037897971383138961</chNFe><dhRecbto>2019-01-28T09:28:46-02:00</dhRecbto><nProt>131193184729831</nProt><digVal>6JJrStroA3+e8Qb7NMqK95osiH8=</digVal><cStat>100</cStat><xMotivo>Autorizado o uso da NF-e</xMotivo></infProt></protNFe></nfeProc>
