<nfeProc xmlns="http://www.portalfiscal.inf.br/nfe" versao="4.00"><NFe xmlns="http://www.portalfiscal.inf.br/nfe"><infNFe Id="NFe13200834516088000110550160006174491020514176" versao="4.00"><ide><cUF>13</cUF><cNF>02051417</cNF><natOp>Venda produção do estabelecimento</natOp><mod>55</mod><serie>16</serie><nNF>617449</nNF><dhEmi>2020-08-17T10:29:38-04:00</dhEmi><tpNF>1</tpNF><idDest>2</idDest><cMunFG>1302603</cMunFG><tpImp>1</tpImp><tpEmis>1</tpEmis><cDV>6</cDV><tpAmb>1</tpAmb><finNFe>1</finNFe><indFinal>0</indFinal><indPres>9</indPres><procEmi>0</procEmi><verProc>SAP NFE 10</verProc></ide><emit><CNPJ>34516088000110</CNPJ><xNome>SECULUS DA AMAZÔNIA INDÚSTRIA E COMÉRCIO S/A</xNome><xFant>SECULUS AMAZONIA MANAUS</xFant><enderEmit><xLgr>RUA VOLUNTÁRIOS DA PÁTRIA</xLgr><nro>635</nro><xCpl>0</xCpl><xBairro>VILA DA PRATA</xBairro><cMun>1302603</cMun><xMun>MANAUS</xMun><UF>AM</UF><CEP>69030520</CEP><xPais>Brasil</xPais><fone>9221217600</fone></enderEmit><IE>062009559</IE><IM>5119801</IM><CNAE>4649410</CNAE><CRT>3</CRT></emit><dest><CNPJ>00149895000120</CNPJ><xNome>IRINEIA COMERCIAL LTDA ME</xNome><enderDest><xLgr>R MELO VIANA</xLgr><nro>113</nro><xBairro>CENTRO</xBairro><cMun>3118304</cMun><xMun>CONSELHEIRO LAFAIETE</xMun><UF>MG</UF><CEP>36400070</CEP><cPais>1058</cPais><xPais>Brasil</xPais><fone>3137633716</fone></enderDest><indIEDest>1</indIEDest><IE>1838926970038</IE></dest><det nItem="1"><prod><cProd>20171GPSVBA2</cProd><cEAN>7893689515803</cEAN><xProd>REL PULSO SECULUS B CX E PU ACO DCR-E 76099-8/2014</xProd><NCM>91021110</NCM><CFOP>6101</CFOP><uCom>UN</uCom><qCom>1.0000</qCom><vUnCom>233.0000000000</vUnCom><vProd>233.00</vProd><cEANTrib>7893689515803</cEANTrib><uTrib>UN</uTrib><qTrib>1.0000</qTrib><vUnTrib>233.0000000000</vUnTrib><vSeg>2.10</vSeg><vDesc>22.72</vDesc><indTot>1</indTot><xPed>2900000021.1031</xPed></prod><imposto><ICMS><ICMS00><orig>4</orig><CST>00</CST><modBC>3</modBC><vBC>212.38</vBC><pICMS>12.0000</pICMS><vICMS>25.49</vICMS></ICMS00></ICMS><IPI><cEnq>335</cEnq><IPINT><CST>52</CST></IPINT></IPI><PIS><PISAliq><CST>02</CST><vBC>212.38</vBC><pPIS>1.3000</pPIS><vPIS>2.76</vPIS></PISAliq></PIS><COFINS><COFINSAliq><CST>02</CST><vBC>212.38</vBC><pCOFINS>6.0000</pCOFINS><vCOFINS>12.74</vCOFINS></COFINSAliq></COFINS></imposto><infAdProd>Lei do ICMS Nº 2.826/03 Isenta de IPI, Art 81 Inciso II do Decreto 7.212/2010.</infAdProd></det><det nItem="2"><prod><cProd>20786G0SVNA1</cProd><cEAN>7893689890597</cEAN><xProd>REL PULSO SECULUS CX E PU ACO DCR-E 2019/11399-0</xProd><NCM>91021110</NCM><CFOP>6101</CFOP><uCom>UN</uCom><qCom>1.0000</qCom><vUnCom>127.0000000000</vUnCom><vProd>127.00</vProd><cEANTrib>7893689890597</cEANTrib><uTrib>UN</uTrib><qTrib>1.0000</qTrib><vUnTrib>127.0000000000</vUnTrib><vSeg>1.15</vSeg><vDesc>12.38</vDesc><indTot>1</indTot><xPed>2900000021.1031</xPed></prod><imposto><ICMS><ICMS00><orig>4</orig><CST>00</CST><modBC>3</modBC><vBC>115.77</vBC><pICMS>12.0000</pICMS><vICMS>13.89</vICMS></ICMS00></ICMS><IPI><cEnq>335</cEnq><IPINT><CST>52</CST></IPINT></IPI><PIS><PISAliq><CST>02</CST><vBC>115.77</vBC><pPIS>1.3000</pPIS><vPIS>1.51</vPIS></PISAliq></PIS><COFINS><COFINSAliq><CST>02</CST><vBC>115.77</vBC><pCOFINS>6.0000</pCOFINS><vCOFINS>6.95</vCOFINS></COFINSAliq></COFINS></imposto><infAdProd>Lei do ICMS Nº 2.826/03 Isenta de IPI, Art 81 Inciso II do Decreto 7.212/2010.</infAdProd></det><det nItem="3"><prod><cProd>20787GPSVDA3</cProd><cEAN>7893689890672</cEAN><xProd>REL PULSO SECULUS F CX E PU ACO DCR-E 2019/11444-0</xProd><NCM>91021110</NCM><CFOP>6101</CFOP><uCom>UN</uCom><qCom>1.0000</qCom><vUnCom>152.0000000000</vUnCom><vProd>152.00</vProd><cEANTrib>7893689890672</cEANTrib><uTrib>UN</uTrib><qTrib>1.0000</qTrib><vUnTrib>152.0000000000</vUnTrib><vSeg>1.37</vSeg><vDesc>14.82</vDesc><indTot>1</indTot><xPed>2900000021.1031</xPed></prod><imposto><ICMS><ICMS00><orig>4</orig><CST>00</CST><modBC>3</modBC><vBC>138.55</vBC><pICMS>12.0000</pICMS><vICMS>16.63</vICMS></ICMS00></ICMS><IPI><cEnq>335</cEnq><IPINT><CST>52</CST></IPINT></IPI><PIS><PISAliq><CST>02</CST><vBC>138.55</vBC><pPIS>1.3000</pPIS><vPIS>1.80</vPIS></PISAliq></PIS><COFINS><COFINSAliq><CST>02</CST><vBC>138.55</vBC><pCOFINS>6.0000</pCOFINS><vCOFINS>8.31</vCOFINS></COFINSAliq></COFINS></imposto><infAdProd>Lei do ICMS Nº 2.826/03 Isenta de IPI, Art 81 Inciso II do Decreto 7.212/2010.</infAdProd></det><det nItem="4"><prod><cProd>20806GPSVDA2</cProd><cEAN>7893689173119</cEAN><xProd>REL PULSO SECULUS F CX E PU ACO DCR-E 2019/12994-3</xProd><NCM>91021110</NCM><CFOP>6101</CFOP><uCom>UN</uCom><qCom>1.0000</qCom><vUnCom>152.0000000000</vUnCom><vProd>152.00</vProd><cEANTrib>7893689173119</cEANTrib><uTrib>UN</uTrib><qTrib>1.0000</qTrib><vUnTrib>152.0000000000</vUnTrib><vSeg>1.37</vSeg><vDesc>14.82</vDesc><indTot>1</indTot><xPed>2900000021.1031</xPed></prod><imposto><ICMS><ICMS00><orig>4</orig><CST>00</CST><modBC>3</modBC><vBC>138.55</vBC><pICMS>12.0000</pICMS><vICMS>16.63</vICMS></ICMS00></ICMS><IPI><cEnq>335</cEnq><IPINT><CST>52</CST></IPINT></IPI><PIS><PISAliq><CST>02</CST><vBC>138.55</vBC><pPIS>1.3000</pPIS><vPIS>1.80</vPIS></PISAliq></PIS><COFINS><COFINSAliq><CST>02</CST><vBC>138.55</vBC><pCOFINS>6.0000</pCOFINS><vCOFINS>8.31</vCOFINS></COFINSAliq></COFINS></imposto><infAdProd>Lei do ICMS Nº 2.826/03 Isenta de IPI, Art 81 Inciso II do Decreto 7.212/2010.</infAdProd></det><det nItem="5"><prod><cProd>20850G0SVNA1</cProd><cEAN>7893689968326</cEAN><xProd>REL PULSO SECULUS CX E PU ACO DCR-E 2020/02383-5</xProd><NCM>91021110</NCM><CFOP>6101</CFOP><uCom>UN</uCom><qCom>1.0000</qCom><vUnCom>127.0000000000</vUnCom><vProd>127.00</vProd><cEANTrib>7893689968326</cEANTrib><uTrib>UN</uTrib><qTrib>1.0000</qTrib><vUnTrib>127.0000000000</vUnTrib><vSeg>1.15</vSeg><vDesc>12.38</vDesc><indTot>1</indTot><xPed>2900000021.1031</xPed></prod><imposto><ICMS><ICMS00><orig>4</orig><CST>00</CST><modBC>3</modBC><vBC>115.77</vBC><pICMS>12.0000</pICMS><vICMS>13.89</vICMS></ICMS00></ICMS><IPI><cEnq>335</cEnq><IPINT><CST>52</CST></IPINT></IPI><PIS><PISAliq><CST>02</CST><vBC>115.77</vBC><pPIS>1.3000</pPIS><vPIS>1.51</vPIS></PISAliq></PIS><COFINS><COFINSAliq><CST>02</CST><vBC>115.77</vBC><pCOFINS>6.0000</pCOFINS><vCOFINS>6.95</vCOFINS></COFINSAliq></COFINS></imposto><infAdProd>Lei do ICMS Nº 2.826/03 Isenta de IPI, Art 81 Inciso II do Decreto 7.212/2010.</infAdProd></det><det nItem="6"><prod><cProd>20850GPSVPA2</cProd><cEAN>7893689968357</cEAN><xProd>REL PULSO SECULUS CX E PU ACO DCR-E 2020/02383-5</xProd><NCM>91021110</NCM><CFOP>6101</CFOP><uCom>UN</uCom><qCom>1.0000</qCom><vUnCom>162.0000000000</vUnCom><vProd>162.00</vProd><cEANTrib>7893689968357</cEANTrib><uTrib>UN</uTrib><qTrib>1.0000</qTrib><vUnTrib>162.0000000000</vUnTrib><vSeg>1.46</vSeg><vDesc>15.80</vDesc><indTot>1</indTot><xPed>2900000021.1031</xPed></prod><imposto><ICMS><ICMS00><orig>4</orig><CST>00</CST><modBC>3</modBC><vBC>147.66</vBC><pICMS>12.0000</pICMS><vICMS>17.72</vICMS></ICMS00></ICMS><IPI><cEnq>335</cEnq><IPINT><CST>52</CST></IPINT></IPI><PIS><PISAliq><CST>02</CST><vBC>147.66</vBC><pPIS>1.3000</pPIS><vPIS>1.92</vPIS></PISAliq></PIS><COFINS><COFINSAliq><CST>02</CST><vBC>147.66</vBC><pCOFINS>6.0000</pCOFINS><vCOFINS>8.86</vCOFINS></COFINSAliq></COFINS></imposto><infAdProd>Lei do ICMS Nº 2.826/03 Isenta de IPI, Art 81 Inciso II do Decreto 7.212/2010.</infAdProd></det><det nItem="7"><prod><cProd>20882G0SVNU2</cProd><cEAN>7893689134912</cEAN><xProd>REL PULSO SECULUS CX ACO PU SILICONE DCR-E 2020/02542-0</xProd><NCM>91021110</NCM><CFOP>6101</CFOP><uCom>UN</uCom><qCom>1.0000</qCom><vUnCom>142.0000000000</vUnCom><vProd>142.00</vProd><cEANTrib>7893689134912</cEANTrib><uTrib>UN</uTrib><qTrib>1.0000</qTrib><vUnTrib>142.0000000000</vUnTrib><vSeg>1.28</vSeg><vDesc>13.85</vDesc><indTot>1</indTot><xPed>2900000021.1031</xPed></prod><imposto><ICMS><ICMS00><orig>4</orig><CST>00</CST><modBC>3</modBC><vBC>129.43</vBC><pICMS>12.0000</pICMS><vICMS>15.53</vICMS></ICMS00></ICMS><IPI><cEnq>335</cEnq><IPINT><CST>52</CST></IPINT></IPI><PIS><PISAliq><CST>02</CST><vBC>129.43</vBC><pPIS>1.3000</pPIS><vPIS>1.68</vPIS></PISAliq></PIS><COFINS><COFINSAliq><CST>02</CST><vBC>129.43</vBC><pCOFINS>6.0000</pCOFINS><vCOFINS>7.77</vCOFINS></COFINSAliq></COFINS></imposto><infAdProd>Lei do ICMS Nº 2.826/03 Isenta de IPI, Art 81 Inciso II do Decreto 7.212/2010.</infAdProd></det><det nItem="8"><prod><cProd>23622G0SVNA2</cProd><cEAN>7893689765697</cEAN><xProd>REL PULSO SECULUS CX E PU ACO DCR-E 2018/07534-3</xProd><NCM>91021110</NCM><CFOP>6101</CFOP><uCom>UN</uCom><qCom>1.0000</qCom><vUnCom>198.0000000000</vUnCom><vProd>198.00</vProd><cEANTrib>7893689765697</cEANTrib><uTrib>UN</uTrib><qTrib>1.0000</qTrib><vUnTrib>198.0000000000</vUnTrib><vSeg>1.79</vSeg><vDesc>19.31</vDesc><indTot>1</indTot><xPed>2900000021.1031</xPed></prod><imposto><ICMS><ICMS00><orig>4</orig><CST>00</CST><modBC>3</modBC><vBC>180.48</vBC><pICMS>12.0000</pICMS><vICMS>21.66</vICMS></ICMS00></ICMS><IPI><cEnq>335</cEnq><IPINT><CST>52</CST></IPINT></IPI><PIS><PISAliq><CST>02</CST><vBC>180.48</vBC><pPIS>1.3000</pPIS><vPIS>2.35</vPIS></PISAliq></PIS><COFINS><COFINSAliq><CST>02</CST><vBC>180.48</vBC><pCOFINS>6.0000</pCOFINS><vCOFINS>10.83</vCOFINS></COFINSAliq></COFINS></imposto><infAdProd>Lei do ICMS Nº 2.826/03 Isenta de IPI, Art 81 Inciso II do Decreto 7.212/2010.</infAdProd></det><det nItem="9"><prod><cProd>23689GPSVDA1</cProd><cEAN>7893689171337</cEAN><xProd>REL PULSO SECULUS F CX E PU ACO DCR-E 2020/01587-5</xProd><NCM>91021110</NCM><CFOP>6101</CFOP><uCom>UN</uCom><qCom>1.0000</qCom><vUnCom>233.0000000000</vUnCom><vProd>233.00</vProd><cEANTrib>7893689171337</cEANTrib><uTrib>UN</uTrib><qTrib>1.0000</qTrib><vUnTrib>233.0000000000</vUnTrib><vSeg>2.10</vSeg><vDesc>22.72</vDesc><indTot>1</indTot><xPed>2900000021.1031</xPed></prod><imposto><ICMS><ICMS00><orig>4</orig><CST>00</CST><modBC>3</modBC><vBC>212.38</vBC><pICMS>12.0000</pICMS><vICMS>25.49</vICMS></ICMS00></ICMS><IPI><cEnq>335</cEnq><IPINT><CST>52</CST></IPINT></IPI><PIS><PISAliq><CST>02</CST><vBC>212.38</vBC><pPIS>1.3000</pPIS><vPIS>2.76</vPIS></PISAliq></PIS><COFINS><COFINSAliq><CST>02</CST><vBC>212.38</vBC><pCOFINS>6.0000</pCOFINS><vCOFINS>12.74</vCOFINS></COFINSAliq></COFINS></imposto><infAdProd>Lei do ICMS Nº 2.826/03 Isenta de IPI, Art 81 Inciso II do Decreto 7.212/2010.</infAdProd></det><det nItem="10"><prod><cProd>23675G0SVNA1</cProd><cEAN>7893689808257</cEAN><xProd>REL PULSO SECULUS CX E PU ACO DCR-E 2018/20302-3</xProd><NCM>91021110</NCM><CFOP>6101</CFOP><uCom>UN</uCom><qCom>1.0000</qCom><vUnCom>162.0000000000</vUnCom><vProd>162.00</vProd><cEANTrib>7893689808257</cEANTrib><uTrib>UN</uTrib><qTrib>1.0000</qTrib><vUnTrib>162.0000000000</vUnTrib><vSeg>1.54</vSeg><vDesc>8.10</vDesc><indTot>1</indTot><xPed>2900000021.1031</xPed></prod><imposto><ICMS><ICMS00><orig>4</orig><CST>00</CST><modBC>3</modBC><vBC>155.44</vBC><pICMS>12.0000</pICMS><vICMS>18.65</vICMS></ICMS00></ICMS><IPI><cEnq>335</cEnq><IPINT><CST>52</CST></IPINT></IPI><PIS><PISAliq><CST>02</CST><vBC>155.44</vBC><pPIS>1.3000</pPIS><vPIS>2.02</vPIS></PISAliq></PIS><COFINS><COFINSAliq><CST>02</CST><vBC>155.44</vBC><pCOFINS>6.0000</pCOFINS><vCOFINS>9.33</vCOFINS></COFINSAliq></COFINS></imposto><infAdProd>Lei do ICMS Nº 2.826/03 Isenta de IPI, Art 81 Inciso II do Decreto 7.212/2010.</infAdProd></det><det nItem="11"><prod><cProd>35000G0SVNA2</cProd><cEAN>7893689808387</cEAN><xProd>REL PULSO SECULUS CX E PU ACO DCR-E 2018/19982-4</xProd><NCM>91021110</NCM><CFOP>6101</CFOP><uCom>UN</uCom><qCom>1.0000</qCom><vUnCom>140.0000000000</vUnCom><vProd>140.00</vProd><cEANTrib>7893689808387</cEANTrib><uTrib>UN</uTrib><qTrib>1.0000</qTrib><vUnTrib>140.0000000000</vUnTrib><vSeg>1.33</vSeg><vDesc>7.00</vDesc><indTot>1</indTot><xPed>2900000021.1031</xPed></prod><imposto><ICMS><ICMS00><orig>4</orig><CST>00</CST><modBC>3</modBC><vBC>134.33</vBC><pICMS>12.0000</pICMS><vICMS>16.12</vICMS></ICMS00></ICMS><IPI><cEnq>335</cEnq><IPINT><CST>52</CST></IPINT></IPI><PIS><PISAliq><CST>02</CST><vBC>134.33</vBC><pPIS>1.3000</pPIS><vPIS>1.75</vPIS></PISAliq></PIS><COFINS><COFINSAliq><CST>02</CST><vBC>134.33</vBC><pCOFINS>6.0000</pCOFINS><vCOFINS>8.06</vCOFINS></COFINSAliq></COFINS></imposto><infAdProd>Lei do ICMS Nº 2.826/03 Isenta de IPI, Art 81 Inciso II do Decreto 7.212/2010.</infAdProd></det><det nItem="12"><prod><cProd>28933G0SKNA2K1</cProd><cEAN>7909669015628</cEAN><xProd>REL PULSO SECULUS CX E PU ACO DCR-E 2020/03442-0</xProd><NCM>91021110</NCM><CFOP>6101</CFOP><uCom>UN</uCom><qCom>1.0000</qCom><vUnCom>213.0000000000</vUnCom><vProd>213.00</vProd><cEANTrib>7909669015628</cEANTrib><uTrib>UN</uTrib><qTrib>1.0000</qTrib><vUnTrib>213.0000000000</vUnTrib><vSeg>1.92</vSeg><vDesc>20.77</vDesc><indTot>1</indTot><xPed>2900000021.1031</xPed></prod><imposto><ICMS><ICMS00><orig>4</orig><CST>00</CST><modBC>3</modBC><vBC>194.15</vBC><pICMS>12.0000</pICMS><vICMS>23.30</vICMS></ICMS00></ICMS><IPI><cEnq>335</cEnq><IPINT><CST>52</CST></IPINT></IPI><PIS><PISAliq><CST>02</CST><vBC>194.15</vBC><pPIS>1.3000</pPIS><vPIS>2.52</vPIS></PISAliq></PIS><COFINS><COFINSAliq><CST>02</CST><vBC>194.15</vBC><pCOFINS>6.0000</pCOFINS><vCOFINS>11.65</vCOFINS></COFINSAliq></COFINS></imposto><infAdProd>Lei do ICMS Nº 2.826/03 Isenta de IPI, Art 81 Inciso II do Decreto 7.212/2010.</infAdProd></det><det nItem="13"><prod><cProd>35001GPSKDA1K1</cProd><cEAN>7893689871237</cEAN><xProd>REL PULSO SECULUS F CX E PU ACO DCR-E 2018/16739-6</xProd><NCM>91021110</NCM><CFOP>6101</CFOP><uCom>UN</uCom><qCom>1.0000</qCom><vUnCom>233.0000000000</vUnCom><vProd>233.00</vProd><cEANTrib>7893689871237</cEANTrib><uTrib>UN</uTrib><qTrib>1.0000</qTrib><vUnTrib>233.0000000000</vUnTrib><vSeg>2.10</vSeg><vDesc>22.72</vDesc><indTot>1</indTot><xPed>2900000021.1031</xPed></prod><imposto><ICMS><ICMS00><orig>4</orig><CST>00</CST><modBC>3</modBC><vBC>212.38</vBC><pICMS>12.0000</pICMS><vICMS>25.49</vICMS></ICMS00></ICMS><IPI><cEnq>335</cEnq><IPINT><CST>52</CST></IPINT></IPI><PIS><PISAliq><CST>02</CST><vBC>212.38</vBC><pPIS>1.3000</pPIS><vPIS>2.76</vPIS></PISAliq></PIS><COFINS><COFINSAliq><CST>02</CST><vBC>212.38</vBC><pCOFINS>6.0000</pCOFINS><vCOFINS>12.74</vCOFINS></COFINSAliq></COFINS></imposto><infAdProd>Lei do ICMS Nº 2.826/03 Isenta de IPI, Art 81 Inciso II do Decreto 7.212/2010.</infAdProd></det><det nItem="14"><prod><cProd>77035G0SVNA1K1</cProd><cEAN>7909669015499</cEAN><xProd>REL PULSO SECULUS CX E PU ACO DCR-E 2020/03442-0</xProd><NCM>91021110</NCM><CFOP>6101</CFOP><uCom>UN</uCom><qCom>1.0000</qCom><vUnCom>162.0000000000</vUnCom><vProd>162.00</vProd><cEANTrib>7909669015499</cEANTrib><uTrib>UN</uTrib><qTrib>1.0000</qTrib><vUnTrib>162.0000000000</vUnTrib><vSeg>1.46</vSeg><vDesc>15.80</vDesc><indTot>1</indTot><xPed>2900000021.1031</xPed></prod><imposto><ICMS><ICMS00><orig>4</orig><CST>00</CST><modBC>3</modBC><vBC>147.66</vBC><pICMS>12.0000</pICMS><vICMS>17.72</vICMS></ICMS00></ICMS><IPI><cEnq>335</cEnq><IPINT><CST>52</CST></IPINT></IPI><PIS><PISAliq><CST>02</CST><vBC>147.66</vBC><pPIS>1.3000</pPIS><vPIS>1.92</vPIS></PISAliq></PIS><COFINS><COFINSAliq><CST>02</CST><vBC>147.66</vBC><pCOFINS>6.0000</pCOFINS><vCOFINS>8.86</vCOFINS></COFINSAliq></COFINS></imposto><infAdProd>Lei do ICMS Nº 2.826/03 Isenta de IPI, Art 81 Inciso II do Decreto 7.212/2010.</infAdProd></det><det nItem="15"><prod><cProd>20868LPSVDA1</cProd><cEAN>7893689160317</cEAN><xProd>REL PULSO SECULUS F CX E PU ACO DCR-E 2020/00937-9</xProd><NCM>91021110</NCM><CFOP>6101</CFOP><uCom>UN</uCom><qCom>1.0000</qCom><vUnCom>198.0000000000</vUnCom><vProd>198.00</vProd><cEANTrib>7893689160317</cEANTrib><uTrib>UN</uTrib><qTrib>1.0000</qTrib><vUnTrib>198.0000000000</vUnTrib><vSeg>1.79</vSeg><vDesc>19.31</vDesc><indTot>1</indTot><xPed>2900000021.1031</xPed></prod><imposto><ICMS><ICMS00><orig>4</orig><CST>00</CST><modBC>3</modBC><vBC>180.48</vBC><pICMS>12.0000</pICMS><vICMS>21.66</vICMS></ICMS00></ICMS><IPI><cEnq>335</cEnq><IPINT><CST>52</CST></IPINT></IPI><PIS><PISAliq><CST>02</CST><vBC>180.48</vBC><pPIS>1.3000</pPIS><vPIS>2.35</vPIS></PISAliq></PIS><COFINS><COFINSAliq><CST>02</CST><vBC>180.48</vBC><pCOFINS>6.0000</pCOFINS><vCOFINS>10.83</vCOFINS></COFINSAliq></COFINS></imposto><infAdProd>Lei do ICMS Nº 2.826/03 Isenta de IPI, Art 81 Inciso II do Decreto 7.212/2010.</infAdProd></det><det nItem="16"><prod><cProd>20888LPSVDA1</cProd><cEAN>7893689149411</cEAN><xProd>REL PULSO SECULUS F CX E PU ACO DCR-E 2020/04031-4</xProd><NCM>91021110</NCM><CFOP>6101</CFOP><uCom>UN</uCom><qCom>1.0000</qCom><vUnCom>162.0000000000</vUnCom><vProd>162.00</vProd><cEANTrib>7893689149411</cEANTrib><uTrib>UN</uTrib><qTrib>1.0000</qTrib><vUnTrib>162.0000000000</vUnTrib><vSeg>1.46</vSeg><vDesc>15.80</vDesc><indTot>1</indTot><xPed>2900000021.1031</xPed></prod><imposto><ICMS><ICMS00><orig>4</orig><CST>00</CST><modBC>3</modBC><vBC>147.66</vBC><pICMS>12.0000</pICMS><vICMS>17.72</vICMS></ICMS00></ICMS><IPI><cEnq>335</cEnq><IPINT><CST>52</CST></IPINT></IPI><PIS><PISAliq><CST>02</CST><vBC>147.66</vBC><pPIS>1.3000</pPIS><vPIS>1.92</vPIS></PISAliq></PIS><COFINS><COFINSAliq><CST>02</CST><vBC>147.66</vBC><pCOFINS>6.0000</pCOFINS><vCOFINS>8.86</vCOFINS></COFINSAliq></COFINS></imposto><infAdProd>Lei do ICMS Nº 2.826/03 Isenta de IPI, Art 81 Inciso II do Decreto 7.212/2010.</infAdProd></det><det nItem="17"><prod><cProd>20887LPSVDA2</cProd><cEAN>7893689149282</cEAN><xProd>REL PULSO SECULUS F CX E PU ACO DCR-E 2020/04031-4</xProd><NCM>91021110</NCM><CFOP>6101</CFOP><uCom>UN</uCom><qCom>1.0000</qCom><vUnCom>162.0000000000</vUnCom><vProd>162.00</vProd><cEANTrib>7893689149282</cEANTrib><uTrib>UN</uTrib><qTrib>1.0000</qTrib><vUnTrib>162.0000000000</vUnTrib><vSeg>1.46</vSeg><vDesc>15.80</vDesc><indTot>1</indTot><xPed>2900000021.1031</xPed></prod><imposto><ICMS><ICMS00><orig>4</orig><CST>00</CST><modBC>3</modBC><vBC>147.66</vBC><pICMS>12.0000</pICMS><vICMS>17.72</vICMS></ICMS00></ICMS><IPI><cEnq>335</cEnq><IPINT><CST>52</CST></IPINT></IPI><PIS><PISAliq><CST>02</CST><vBC>147.66</vBC><pPIS>1.3000</pPIS><vPIS>1.92</vPIS></PISAliq></PIS><COFINS><COFINSAliq><CST>02</CST><vBC>147.66</vBC><pCOFINS>6.0000</pCOFINS><vCOFINS>8.86</vCOFINS></COFINSAliq></COFINS></imposto><infAdProd>Lei do ICMS Nº 2.826/03 Isenta de IPI, Art 81 Inciso II do Decreto 7.212/2010.</infAdProd></det><det nItem="18"><prod><cProd>20887L0SVNA1</cProd><cEAN>7893689149275</cEAN><xProd>REL PULSO SECULUS CX E PU ACO DCR-E 2020/04031-4</xProd><NCM>91021110</NCM><CFOP>6101</CFOP><uCom>UN</uCom><qCom>1.0000</qCom><vUnCom>142.0000000000</vUnCom><vProd>142.00</vProd><cEANTrib>7893689149275</cEANTrib><uTrib>UN</uTrib><qTrib>1.0000</qTrib><vUnTrib>142.0000000000</vUnTrib><vSeg>1.28</vSeg><vDesc>13.85</vDesc><indTot>1</indTot><xPed>2900000021.1031</xPed></prod><imposto><ICMS><ICMS00><orig>4</orig><CST>00</CST><modBC>3</modBC><vBC>129.43</vBC><pICMS>12.0000</pICMS><vICMS>15.53</vICMS></ICMS00></ICMS><IPI><cEnq>335</cEnq><IPINT><CST>52</CST></IPINT></IPI><PIS><PISAliq><CST>02</CST><vBC>129.43</vBC><pPIS>1.3000</pPIS><vPIS>1.68</vPIS></PISAliq></PIS><COFINS><COFINSAliq><CST>02</CST><vBC>129.43</vBC><pCOFINS>6.0000</pCOFINS><vCOFINS>7.77</vCOFINS></COFINSAliq></COFINS></imposto><infAdProd>Lei do ICMS Nº 2.826/03 Isenta de IPI, Art 81 Inciso II do Decreto 7.212/2010.</infAdProd></det><det nItem="19"><prod><cProd>23619LPSVPS3</cProd><cEAN>7893689889843</cEAN><xProd>REL PULSO SECULUS CX MET PU ACO DCR-E 2019/11656-6</xProd><NCM>91021110</NCM><CFOP>6101</CFOP><uCom>UN</uCom><qCom>1.0000</qCom><vUnCom>162.0000000000</vUnCom><vProd>162.00</vProd><cEANTrib>7893689889843</cEANTrib><uTrib>UN</uTrib><qTrib>1.0000</qTrib><vUnTrib>162.0000000000</vUnTrib><vSeg>1.46</vSeg><vDesc>15.80</vDesc><indTot>1</indTot><xPed>2900000021.1031</xPed></prod><imposto><ICMS><ICMS00><orig>4</orig><CST>00</CST><modBC>3</modBC><vBC>147.66</vBC><pICMS>12.0000</pICMS><vICMS>17.72</vICMS></ICMS00></ICMS><IPI><cEnq>335</cEnq><IPINT><CST>52</CST></IPINT></IPI><PIS><PISAliq><CST>02</CST><vBC>147.66</vBC><pPIS>1.3000</pPIS><vPIS>1.92</vPIS></PISAliq></PIS><COFINS><COFINSAliq><CST>02</CST><vBC>147.66</vBC><pCOFINS>6.0000</pCOFINS><vCOFINS>8.86</vCOFINS></COFINSAliq></COFINS></imposto><infAdProd>Lei do ICMS Nº 2.826/03 Isenta de IPI, Art 81 Inciso II do Decreto 7.212/2010.</infAdProd></det><det nItem="20"><prod><cProd>77050L0SVNS4</cProd><cEAN>7893689161970</cEAN><xProd>REL PULSO SECULUS CX MET PU ACO DCR-E 2019/18225-9</xProd><NCM>91021110</NCM><CFOP>6101</CFOP><uCom>UN</uCom><qCom>1.0000</qCom><vUnCom>142.0000000000</vUnCom><vProd>142.00</vProd><cEANTrib>7893689161970</cEANTrib><uTrib>UN</uTrib><qTrib>1.0000</qTrib><vUnTrib>142.0000000000</vUnTrib><vSeg>1.28</vSeg><vDesc>13.85</vDesc><indTot>1</indTot><xPed>2900000021.1031</xPed></prod><imposto><ICMS><ICMS00><orig>4</orig><CST>00</CST><modBC>3</modBC><vBC>129.43</vBC><pICMS>12.0000</pICMS><vICMS>15.53</vICMS></ICMS00></ICMS><IPI><cEnq>335</cEnq><IPINT><CST>52</CST></IPINT></IPI><PIS><PISAliq><CST>02</CST><vBC>129.43</vBC><pPIS>1.3000</pPIS><vPIS>1.68</vPIS></PISAliq></PIS><COFINS><COFINSAliq><CST>02</CST><vBC>129.43</vBC><pCOFINS>6.0000</pCOFINS><vCOFINS>7.77</vCOFINS></COFINSAliq></COFINS></imposto><infAdProd>Lei do ICMS Nº 2.826/03 Isenta de IPI, Art 81 Inciso II do Decreto 7.212/2010.</infAdProd></det><det nItem="21"><prod><cProd>77050LPSVDS1K1</cProd><cEAN>7909669021667</cEAN><xProd>REL PULSO SECULUS F CX METAL PU ACO DCR-E 2020/07403-0</xProd><NCM>91021110</NCM><CFOP>6101</CFOP><uCom>UN</uCom><qCom>1.0000</qCom><vUnCom>152.0000000000</vUnCom><vProd>152.00</vProd><cEANTrib>7909669021667</cEANTrib><uTrib>UN</uTrib><qTrib>1.0000</qTrib><vUnTrib>152.0000000000</vUnTrib><vSeg>1.37</vSeg><vDesc>14.82</vDesc><indTot>1</indTot><xPed>2900000021.1031</xPed></prod><imposto><ICMS><ICMS00><orig>4</orig><CST>00</CST><modBC>3</modBC><vBC>138.55</vBC><pICMS>12.0000</pICMS><vICMS>16.63</vICMS></ICMS00></ICMS><IPI><cEnq>335</cEnq><IPINT><CST>52</CST></IPINT></IPI><PIS><PISAliq><CST>02</CST><vBC>138.55</vBC><pPIS>1.3000</pPIS><vPIS>1.80</vPIS></PISAliq></PIS><COFINS><COFINSAliq><CST>02</CST><vBC>138.55</vBC><pCOFINS>6.0000</pCOFINS><vCOFINS>8.31</vCOFINS></COFINSAliq></COFINS></imposto><infAdProd>Lei do ICMS Nº 2.826/03 Isenta de IPI, Art 81 Inciso II do Decreto 7.212/2010.</infAdProd></det><det nItem="22"><prod><cProd>77067LPSVDS1</cProd><cEAN>7893689171283</cEAN><xProd>REL PULSO SECULUS F CX METAL PU ACO DCR-E 2020/01836-0</xProd><NCM>91021110</NCM><CFOP>6101</CFOP><uCom>UN</uCom><qCom>1.0000</qCom><vUnCom>162.0000000000</vUnCom><vProd>162.00</vProd><cEANTrib>7893689171283</cEANTrib><uTrib>UN</uTrib><qTrib>1.0000</qTrib><vUnTrib>162.0000000000</vUnTrib><vSeg>1.46</vSeg><vDesc>15.80</vDesc><indTot>1</indTot><xPed>2900000021.1031</xPed></prod><imposto><ICMS><ICMS00><orig>4</orig><CST>00</CST><modBC>3</modBC><vBC>147.66</vBC><pICMS>12.0000</pICMS><vICMS>17.72</vICMS></ICMS00></ICMS><IPI><cEnq>335</cEnq><IPINT><CST>52</CST></IPINT></IPI><PIS><PISAliq><CST>02</CST><vBC>147.66</vBC><pPIS>1.3000</pPIS><vPIS>1.92</vPIS></PISAliq></PIS><COFINS><COFINSAliq><CST>02</CST><vBC>147.66</vBC><pCOFINS>6.0000</pCOFINS><vCOFINS>8.86</vCOFINS></COFINSAliq></COFINS></imposto><infAdProd>Lei do ICMS Nº 2.826/03 Isenta de IPI, Art 81 Inciso II do Decreto 7.212/2010.</infAdProd></det><det nItem="23"><prod><cProd>77073L0SVNS2</cProd><cEAN>7893689957917</cEAN><xProd>REL PULSO SECULUS CX METAL PU ACO DCR-E 2020/02793-8</xProd><NCM>91021110</NCM><CFOP>6101</CFOP><uCom>UN</uCom><qCom>1.0000</qCom><vUnCom>162.0000000000</vUnCom><vProd>162.00</vProd><cEANTrib>7893689957917</cEANTrib><uTrib>UN</uTrib><qTrib>1.0000</qTrib><vUnTrib>162.0000000000</vUnTrib><vSeg>1.46</vSeg><vDesc>15.80</vDesc><indTot>1</indTot><xPed>2900000021.1031</xPed></prod><imposto><ICMS><ICMS00><orig>4</orig><CST>00</CST><modBC>3</modBC><vBC>147.66</vBC><pICMS>12.0000</pICMS><vICMS>17.72</vICMS></ICMS00></ICMS><IPI><cEnq>335</cEnq><IPINT><CST>52</CST></IPINT></IPI><PIS><PISAliq><CST>02</CST><vBC>147.66</vBC><pPIS>1.3000</pPIS><vPIS>1.92</vPIS></PISAliq></PIS><COFINS><COFINSAliq><CST>02</CST><vBC>147.66</vBC><pCOFINS>6.0000</pCOFINS><vCOFINS>8.86</vCOFINS></COFINSAliq></COFINS></imposto><infAdProd>Lei do ICMS Nº 2.826/03 Isenta de IPI, Art 81 Inciso II do Decreto 7.212/2010.</infAdProd></det><total><ICMSTot><vBC>3551.12</vBC><vICMS>426.16</vICMS><vICMSDeson>0.00</vICMSDeson><vFCP>0.00</vFCP><vBCST>0.00</vBCST><vST>0.00</vST><vFCPST>0.00</vFCPST><vFCPSTRet>0.00</vFCPSTRet><vProd>3880.00</vProd><vFrete>0.00</vFrete><vSeg>35.14</vSeg><vDesc>364.02</vDesc><vII>0.00</vII><vIPI>0.00</vIPI><vIPIDevol>0.00</vIPIDevol><vPIS>46.17</vPIS><vCOFINS>213.08</vCOFINS><vOutro>0.00</vOutro><vNF>3551.12</vNF></ICMSTot></total><transp><modFrete>0</modFrete><transporta><CNPJ>95591723011587</CNPJ><xNome>TNT MERCURIO CARGAS E ENCOMENDAS EX AS S A</xNome><IE>042081793</IE><xEnder>AV DOS OITIS 1607</xEnder><xMun>MANAUS</xMun><UF>AM</UF></transporta><vol><qVol>1</qVol><pesoL>6.893</pesoL><pesoB>6.893</pesoB></vol></transp><cobr><fat><nFat>0000617449</nFat><vOrig>3915.14</vOrig><vDesc>364.02</vDesc><vLiq>3551.12</vLiq></fat><dup><nDup>001</nDup><dVenc>2020-08-31</dVenc><vDup>3551.12</vDup></dup></cobr><pag><detPag><tPag>14</tPag><vPag>3551.12</vPag></detPag></pag><infAdic><infCpl>Ordem(s) de Venda: 1130584 - Doc. Faturamento: 0091329855 DCI Mensal Produz ZFM-Resol.Suframa nº027/2011-Insc.Suframa nº200166034. Quantidade de peças: 23,000 Valor de impostos incidentes conf. lei 12741/12: 685,41</infCpl></infAdic><infRespTec><CNPJ>74544297000192</CNPJ><xContato>SAP BRASIL LTDA</xContato><email>TI@SECULUS.COM.BR</email><fone>3135167600</fone></infRespTec></infNFe><Signature xmlns="http://www.w3.org/2000/09/xmldsig#"><SignedInfo><CanonicalizationMethod Algorithm="http://www.w3.org/TR/2001/REC-xml-c14n-20010315" /><SignatureMethod Algorithm="http://www.w3.org/2000/09/xmldsig#rsa-sha1" /><Reference URI="#NFe13200834516088000110550160006174491020514176"><Transforms><Transform Algorithm="http://www.w3.org/2000/09/xmldsig#enveloped-signature" /><Transform Algorithm="http://www.w3.org/TR/2001/REC-xml-c14n-20010315" /></Transforms><DigestMethod Algorithm="http://www.w3.org/2000/09/xmldsig#sha1" /><DigestValue>LiFFwEG9x5WAIo09m23d0ti0Xsw=</DigestValue></Reference></SignedInfo><SignatureValue>H1N1i6/AMql7r5j07LRiSW17QlJ6pHWwxA42A3L/CoZDb53P/tppSQ2sSsgZ1zC0biqRPoZonkEM
p6pyODMJMxGn7D4cijjwjDxMyO5AYNYw+U44N+ZlLugKoIw8/43BPtAWiXB3OvTYbktoJe7cJehF
FjZWxxrx/FIrLuC2BAYpRmLl5vM7k9UpokmP2g+ux9YvzMc3kncIQapINQBQUf9obICCVobxe+8n
+7IGcbDcU4dwswWDZORcqU8n8lG4vWrbtWKUGBK7tyrDoUA2G53cCfNE7T7RRBu0pA0XDszadRsN
0QS7cYW1mJrGE0gx4laueSB2ljljG9Mz2UjGaQ==</SignatureValue><KeyInfo><X509Data><X509Certificate>MIIHwzCCBaugAwIBAgIIW0AhcMM3rSkwDQYJKoZIhvcNAQELBQAwczELMAkGA1UEBhMCQlIxEzAR
BgNVBAoTCklDUC1CcmFzaWwxNjA0BgNVBAsTLVNlY3JldGFyaWEgZGEgUmVjZWl0YSBGZWRlcmFs
IGRvIEJyYXNpbCAtIFJGQjEXMBUGA1UEAxMOQUMgTElOSyBSRkIgdjIwHhcNMjAwMjEzMTc0ODI2
WhcNMjEwMjEzMTc0ODI2WjCB7zELMAkGA1UEBhMCQlIxCzAJBgNVBAgTAkFNMQ8wDQYDVQQHEwZN
QU5BVVMxEzARBgNVBAoTCklDUC1CcmFzaWwxNjA0BgNVBAsTLVNlY3JldGFyaWEgZGEgUmVjZWl0
YSBGZWRlcmFsIGRvIEJyYXNpbCAtIFJGQjEWMBQGA1UECxMNUkZCIGUtQ05QSiBBMTEXMBUGA1UE
CxMOMTE1MDgyMjIwMDAxMzYxRDBCBgNVBAMTO1NFQ1VMVVMgREEgQU1BWk9OSUEgSU5EVVNUUklB
IEUgQ09NRVJDSU8gUyBBOjM0NTE2MDg4MDAwMTEwMIIBIjANBgkqhkiG9w0BAQEFAAOCAQ8AMIIB
CgKCAQEAxNZjRXfxspICYDTRHoUCrHWQCu85naBN5Oi0w3oeI6+0kJ+jef/UKIrTqQTlWDMVuPt8
XjOy6IZt3By6Wp8Veq2U36rHPcXLqlB55C/pYsQw1Ko+ax6OMz/1BJjvD9/cPdM83w5dbBM05kHT
BKCVKc0QXeHB+HC3KpsumZl/7n46lSc4gaCmiaIV4W3LwkNLALzTZC4/6S3VSc0Q4Z8lb43h9Rnq
Jy018tIrvlWmDoaS4/54XxN4HFHie+BYPlmDKuLDP2WuYOKKgXgrX44UhHThCmKKJkLwMDuOcVce
Tz1nq84aKZLmgxyOQ6OCqtvGT7puwxoNvIk6y6FKTJNoqQIDAQABo4IC3DCCAtgwHwYDVR0jBBgw
FoAUDd/WR/QTTuUiWDIsZqbnLuRXvAIwDgYDVR0PAQH/BAQDAgXgMG4GA1UdIARnMGUwYwYGYEwB
AgE7MFkwVwYIKwYBBQUHAgEWS2h0dHA6Ly9yZXBvc2l0b3Jpby5saW5rY2VydGlmaWNhY2FvLmNv
bS5ici9hYy1saW5rcmZiL2FjLWxpbmstcmZiLXBjLWExLnBkZjCBsAYDVR0fBIGoMIGlMFCgTqBM
hkpodHRwOi8vcmVwb3NpdG9yaW8ubGlua2NlcnRpZmljYWNhby5jb20uYnIvYWMtbGlua3JmYi9s
Y3ItYWMtbGlua3JmYnY1LmNybDBRoE+gTYZLaHR0cDovL3JlcG9zaXRvcmlvMi5saW5rY2VydGlm
aWNhY2FvLmNvbS5ici9hYy1saW5rcmZiL2xjci1hYy1saW5rcmZidjUuY3JsMIGVBggrBgEFBQcB
AQSBiDCBhTBSBggrBgEFBQcwAoZGaHR0cDovL3JlcG9zaXRvcmlvLmxpbmtjZXJ0aWZpY2FjYW8u
Y29tLmJyL2FjLWxpbmtyZmIvYWMtbGlua3JmYnY1LnA3YjAvBggrBgEFBQcwAYYjaHR0cDovL29j
c3AubGlua2NlcnRpZmljYWNhby5jb20uYnIwgb8GA1UdEQSBtzCBtIEbU0VSR0lPLkFSVFVSQFNF
Q1VMVVMuQ09NLkJSoCcGBWBMAQMCoB4THEFMRVhBTkRSRSBMVUlaIFNJTFZBIEFaRVZFRE+gGQYF
YEwBAwOgEBMOMzQ1MTYwODgwMDAxMTCgOAYFYEwBAwSgLxMtMTExMjE5NzE4ODM2NDUzNDY1MzAw
MDAwMDAwMDAwMDAwMDAwMDAwMDAwMDAwoBcGBWBMAQMHoA4TDDAwMDAwMDAwMDAwMDAdBgNVHSUE
FjAUBggrBgEFBQcDAgYIKwYBBQUHAwQwCQYDVR0TBAIwADANBgkqhkiG9w0BAQsFAAOCAgEAb7Vs
uCMB7hHsNLJk2kQP85gLQDEHviQfo76eZuoKGTNu/T2dtAbXduAzVtyRkjCBadOoPxNei0vhOzMx
cTRb/LkSnmWxdUjrj81KgH2fvQZ8cPoC8aUJn/Yf8Qw5eAoWAvDVwxCJRDqkWIjBwnDJz2dOVU0i
AyhoUwSsOrhuB1X4eUEPHjOy+PBq7dk+J+n0l9P0u+Sv4ROIOFn2IJxb7NHoeZLs4tlIr39hjNKp
RwOcSp1riLcTBWNfAsKIAcPZlEvgQCJKpW5XEXg/1FgtnN1jUIrrM0yMGmeUXQ/188iWVVVfiw2I
VyjR0XWQNusrxXJMNcqPJpC7hsoOGmLU4jlX0zMUShklKDgiUxr1a4etJQzn1U2TYcDnMhRA/NGW
C5wgCZR4ANCGzN4w9k7m6MQRYUc12KuP+14HkjRGoj092VVetX4EX+twAHb4W/L2sEiFGTI+CWTQ
mevRitHqRZKEu+e3TgzQISGqCQhtnKWA/5x8kvjdckX8XWbAId3MmoxXogpOnGHFv1vvbur5eFrm
3rKI/uFhvlOacy+ImZVYab0QlXi++esmXuO2TB2CahocM2mm+KXy9Th9nEGuKS7Hm4HpLpXdfImL
Ijb2Rk4GHK1md2hs12mJlYI5/K64iU+Koz6PW1e4L0eKFHiOhPue18XSoWpU5xgsrWNpZ3I=</X509Certificate></X509Data></KeyInfo></Signature></NFe><protNFe xmlns="http://www.portalfiscal.inf.br/nfe" versao="4.00"><infProt Id="ID113201543598124"><tpAmb>1</tpAmb><verAplic>AM4.00</verAplic><chNFe>13200834516088000110550160006174491020514176</chNFe><dhRecbto>2020-08-17T10:30:13-04:00</dhRecbto><nProt>113201543598124</nProt><digVal>LiFFwEG9x5WAIo09m23d0ti0Xsw=</digVal><cStat>100</cStat><xMotivo>Autorizado o uso da NF-e</xMotivo></infProt></protNFe></nfeProc>
