<nfeProc versao="4.00" xmlns="http://www.portalfiscal.inf.br/nfe"><NFe xmlns="http://www.portalfiscal.inf.br/nfe"><infNFe versao="4.00" Id="NFe31190607489678000129550010001358331762995330"><ide><cUF>31</cUF><cNF>76299533</cNF><natOp>VENDA MERC ADQ SUJ ST /</natOp><mod>55</mod><serie>1</serie><nNF>135833</nNF><dhEmi>2019-06-04T09:02:02-03:00</dhEmi><tpNF>1</tpNF><idDest>1</idDest><cMunFG>3118601</cMunFG><tpImp>1</tpImp><tpEmis>1</tpEmis><cDV>0</cDV><tpAmb>1</tpAmb><finNFe>1</finNFe><indFinal>0</indFinal><indPres>9</indPres><procEmi>0</procEmi><verProc>SAP GRC 10.0</verProc></ide><emit><CNPJ>07489678000129</CNPJ><xNome>Sul Mineira Alimentos Ltda.</xNome><enderEmit><xLgr>Av Helena de Vasconcelos Costa</xLgr><nro>1365</nro><xBairro>Cincao</xBairro><cMun>3118601</cMun><xMun>Contagem</xMun><UF>MG</UF><CEP>32371685</CEP><xPais>Brasil</xPais><fone>3130363672</fone></enderEmit><IE>6933700340033</IE><CRT>3</CRT></emit><dest><CNPJ>05859105000114</CNPJ><xNome>AGROPECUARIA MONTANHEZA LTDA ME</xNome><enderDest><xLgr>RUA BENJAMIN CONSTANT LETRA A</xLgr><nro>344</nro><xBairro>SAO JOAO</xBairro><cMun>3118304</cMun><xMun>CONSELHEIRO LAFAIETE</xMun><UF>MG</UF><CEP>36400000</CEP><cPais>1058</cPais><xPais>Brasil</xPais><fone>3137637949</fone></enderDest><indIEDest>1</indIEDest><IE>1832796610023</IE></dest><det nItem="1"><prod><cProd>E00210184</cProd><cEAN>7896588934386</cEAN><xProd>NAT FRANGO PERU &amp; FRUTAS AD RP 15KG</xProd><NCM>23099010</NCM><CEST>2200100</CEST><EXTIPI>01</EXTIPI><CFOP>5405</CFOP><uCom>SC</uCom><qCom>4.0000</qCom><vUnCom>98.2700000000</vUnCom><vProd>393.08</vProd><cEANTrib>07896588934386</cEANTrib><uTrib>SC</uTrib><qTrib>4.0000</qTrib><vUnTrib>98.2700000000</vUnTrib><vFrete>13.75</vFrete><indTot>1</indTot><xPed>2954347</xPed></prod><imposto><ICMS><ICMS60><orig>0</orig><CST>60</CST><vBCSTRet>400.60</vBCSTRet><pST>20.0000</pST><vICMSSubstituto>49.39</vICMSSubstituto><vICMSSTRet>22.72</vICMSSTRet><vBCFCPSTRet>400.60</vBCFCPSTRet><pFCPSTRet>2.0000</pFCPSTRet><vFCPSTRet>8.01</vFCPSTRet></ICMS60></ICMS><IPI><cEnq>999</cEnq><IPITrib><CST>99</CST><vBC>0.00</vBC><pIPI>0.0000</pIPI><vIPI>0.00</vIPI></IPITrib></IPI><PIS><PISAliq><CST>01</CST><vBC>406.83</vBC><pPIS>1.6500</pPIS><vPIS>6.71</vPIS></PISAliq></PIS><COFINS><COFINSAliq><CST>01</CST><vBC>406.83</vBC><pCOFINS>7.6000</pCOFINS><vCOFINS>30.92</vCOFINS></COFINSAliq></COFINS></imposto><infAdProd>ICMS ST Recolhido antecipadamente pelo Fabricante.</infAdProd></det><det nItem="2"><prod><cProd>E00110186</cProd><cEAN>7896588934423</cEAN><xProd>NAT FRANGO PERU &amp; VEGETAIS AD RP 15KG</xProd><NCM>23099010</NCM><CEST>2200100</CEST><EXTIPI>01</EXTIPI><CFOP>5405</CFOP><uCom>SC</uCom><qCom>4.0000</qCom><vUnCom>101.1800000000</vUnCom><vProd>404.72</vProd><cEANTrib>07896588934423</cEANTrib><uTrib>SC</uTrib><qTrib>4.0000</qTrib><vUnTrib>101.1800000000</vUnTrib><vFrete>13.75</vFrete><indTot>1</indTot><xPed>2954347</xPed></prod><imposto><ICMS><ICMS60><orig>0</orig><CST>60</CST><vBCSTRet>426.66</vBCSTRet><pST>20.0000</pST><vICMSSubstituto>52.60</vICMSSubstituto><vICMSSTRet>24.20</vICMSSTRet><vBCFCPSTRet>426.66</vBCFCPSTRet><pFCPSTRet>2.0000</pFCPSTRet><vFCPSTRet>8.53</vFCPSTRet></ICMS60></ICMS><IPI><cEnq>999</cEnq><IPITrib><CST>99</CST><vBC>0.00</vBC><pIPI>0.0000</pIPI><vIPI>0.00</vIPI></IPITrib></IPI><PIS><PISAliq><CST>01</CST><vBC>418.47</vBC><pPIS>1.6500</pPIS><vPIS>6.90</vPIS></PISAliq></PIS><COFINS><COFINSAliq><CST>01</CST><vBC>418.47</vBC><pCOFINS>7.6000</pCOFINS><vCOFINS>31.80</vCOFINS></COFINSAliq></COFINS></imposto><infAdProd>ICMS ST Recolhido antecipadamente pelo Fabricante.</infAdProd></det><det nItem="3"><prod><cProd>E00210351</cProd><cEAN>7896588944750</cEAN><xProd>NAT GATOS AD SALMAO E FRUTAS 10,1KG</xProd><NCM>23099010</NCM><CEST>2200100</CEST><EXTIPI>01</EXTIPI><CFOP>5405</CFOP><uCom>SC</uCom><qCom>5.0000</qCom><vUnCom>84.4100000000</vUnCom><vProd>422.05</vProd><cEANTrib>07896588944750</cEANTrib><uTrib>SC</uTrib><qTrib>5.0000</qTrib><vUnTrib>84.4100000000</vUnTrib><vFrete>11.65</vFrete><indTot>1</indTot><xPed>2954347</xPed></prod><imposto><ICMS><ICMS60><orig>0</orig><CST>60</CST><vBCSTRet>422.47</vBCSTRet><pST>20.0000</pST><vICMSSubstituto>52.09</vICMSSubstituto><vICMSSTRet>23.96</vICMSSTRet><vBCFCPSTRet>422.47</vBCFCPSTRet><pFCPSTRet>2.0000</pFCPSTRet><vFCPSTRet>8.45</vFCPSTRet></ICMS60></ICMS><IPI><cEnq>999</cEnq><IPITrib><CST>99</CST><vBC>0.00</vBC><pIPI>0.0000</pIPI><vIPI>0.00</vIPI></IPITrib></IPI><PIS><PISAliq><CST>01</CST><vBC>433.70</vBC><pPIS>1.6500</pPIS><vPIS>7.16</vPIS></PISAliq></PIS><COFINS><COFINSAliq><CST>01</CST><vBC>433.70</vBC><pCOFINS>7.6000</pCOFINS><vCOFINS>32.96</vCOFINS></COFINSAliq></COFINS></imposto><infAdProd>ICMS ST Recolhido antecipadamente pelo Fabricante.</infAdProd></det><det nItem="4"><prod><cProd>E00007167</cProd><cEAN>0796588949618</cEAN><xProd>DOG LIC DENTAL FRESH CRUNCH 8X45G</xProd><NCM>23091000</NCM><CEST>2200100</CEST><CFOP>5405</CFOP><uCom>CX</uCom><qCom>1.0000</qCom><vUnCom>27.4200000000</vUnCom><vProd>27.42</vProd><cEANTrib>00796588949618</cEANTrib><uTrib>CX</uTrib><qTrib>1.0000</qTrib><vUnTrib>27.4200000000</vUnTrib><vFrete>0.12</vFrete><indTot>1</indTot><xPed>2954347</xPed></prod><imposto><ICMS><ICMS60><orig>0</orig><CST>60</CST><vBCSTRet>20.20</vBCSTRet><pST>20.0000</pST><vICMSSubstituto>2.49</vICMSSubstituto><vICMSSTRet>1.15</vICMSSTRet><vBCFCPSTRet>20.20</vBCFCPSTRet><pFCPSTRet>2.0000</pFCPSTRet><vFCPSTRet>0.40</vFCPSTRet></ICMS60></ICMS><IPI><cEnq>999</cEnq><IPITrib><CST>99</CST><vBC>0.00</vBC><pIPI>0.0000</pIPI><vIPI>0.00</vIPI></IPITrib></IPI><PIS><PISAliq><CST>01</CST><vBC>27.54</vBC><pPIS>1.6500</pPIS><vPIS>0.45</vPIS></PISAliq></PIS><COFINS><COFINSAliq><CST>01</CST><vBC>27.54</vBC><pCOFINS>7.6000</pCOFINS><vCOFINS>2.09</vCOFINS></COFINSAliq></COFINS></imposto><infAdProd>ICMS ST Recolhido antecipadamente pelo Fabricante.</infAdProd></det><det nItem="5"><prod><cProd>E00007163</cProd><cEAN>7896588949601</cEAN><xProd>DOG LIC DENTAL FRESH 12X65G</xProd><NCM>23091000</NCM><CEST>2200100</CEST><CFOP>5405</CFOP><uCom>CX</uCom><qCom>1.0000</qCom><vUnCom>41.5100000000</vUnCom><vProd>41.51</vProd><cEANTrib>07896588949601</cEANTrib><uTrib>CX</uTrib><qTrib>1.0000</qTrib><vUnTrib>41.5100000000</vUnTrib><vFrete>0.24</vFrete><indTot>1</indTot><xPed>2954347</xPed></prod><imposto><ICMS><ICMS60><orig>0</orig><CST>60</CST><vBCSTRet>40.01</vBCSTRet><pST>20.0000</pST><vICMSSubstituto>4.93</vICMSSubstituto><vICMSSTRet>2.27</vICMSSTRet><vBCFCPSTRet>40.01</vBCFCPSTRet><pFCPSTRet>2.0000</pFCPSTRet><vFCPSTRet>0.80</vFCPSTRet></ICMS60></ICMS><IPI><cEnq>999</cEnq><IPITrib><CST>99</CST><vBC>0.00</vBC><pIPI>0.0000</pIPI><vIPI>0.00</vIPI></IPITrib></IPI><PIS><PISAliq><CST>01</CST><vBC>41.75</vBC><pPIS>1.6500</pPIS><vPIS>0.69</vPIS></PISAliq></PIS><COFINS><COFINSAliq><CST>01</CST><vBC>41.75</vBC><pCOFINS>7.6000</pCOFINS><vCOFINS>3.17</vCOFINS></COFINSAliq></COFINS></imposto><infAdProd>ICMS ST Recolhido antecipadamente pelo Fabricante.</infAdProd></det><det nItem="6"><prod><cProd>E00007150</cProd><cEAN>7896588949526</cEAN><xProd>DOG LIC BONE BEEF 30X80G</xProd><NCM>23091000</NCM><CEST>2200100</CEST><CFOP>5405</CFOP><uCom>CX</uCom><qCom>1.0000</qCom><vUnCom>73.6000000000</vUnCom><vProd>73.60</vProd><cEANTrib>07896588949526</cEANTrib><uTrib>CX</uTrib><qTrib>1.0000</qTrib><vUnTrib>73.6000000000</vUnTrib><vFrete>0.59</vFrete><indTot>1</indTot><xPed>2954347</xPed></prod><imposto><ICMS><ICMS60><orig>0</orig><CST>60</CST><vBCSTRet>114.71</vBCSTRet><pST>20.0000</pST><vICMSSubstituto>14.14</vICMSSubstituto><vICMSSTRet>6.51</vICMSSTRet><vBCFCPSTRet>114.71</vBCFCPSTRet><pFCPSTRet>2.0000</pFCPSTRet><vFCPSTRet>2.29</vFCPSTRet></ICMS60></ICMS><IPI><cEnq>999</cEnq><IPITrib><CST>99</CST><vBC>0.00</vBC><pIPI>0.0000</pIPI><vIPI>0.00</vIPI></IPITrib></IPI><PIS><PISAliq><CST>01</CST><vBC>74.19</vBC><pPIS>1.6500</pPIS><vPIS>1.22</vPIS></PISAliq></PIS><COFINS><COFINSAliq><CST>01</CST><vBC>74.19</vBC><pCOFINS>7.6000</pCOFINS><vCOFINS>5.64</vCOFINS></COFINSAliq></COFINS></imposto><infAdProd>ICMS ST Recolhido antecipadamente pelo Fabricante.</infAdProd></det><det nItem="7"><prod><cProd>E00007203</cProd><cEAN>7896588949540</cEAN><xProd>DOG LIC BONE DUO BEEF&amp;BACON 15X(2X80G)</xProd><NCM>23091000</NCM><CEST>2200100</CEST><CFOP>5405</CFOP><uCom>CX</uCom><qCom>1.0000</qCom><vUnCom>64.0600000000</vUnCom><vProd>64.06</vProd><cEANTrib>07896588949540</cEANTrib><uTrib>CX</uTrib><qTrib>1.0000</qTrib><vUnTrib>64.0600000000</vUnTrib><vFrete>0.58</vFrete><indTot>1</indTot><xPed>2954347</xPed></prod><imposto><ICMS><ICMS60><orig>0</orig><CST>60</CST><vBCSTRet>87.57</vBCSTRet><pST>20.0000</pST><vICMSSubstituto>10.80</vICMSSubstituto><vICMSSTRet>4.97</vICMSSTRet><vBCFCPSTRet>87.57</vBCFCPSTRet><pFCPSTRet>2.0000</pFCPSTRet><vFCPSTRet>1.75</vFCPSTRet></ICMS60></ICMS><IPI><cEnq>999</cEnq><IPITrib><CST>99</CST><vBC>0.00</vBC><pIPI>0.0000</pIPI><vIPI>0.00</vIPI></IPITrib></IPI><PIS><PISAliq><CST>01</CST><vBC>64.64</vBC><pPIS>1.6500</pPIS><vPIS>1.07</vPIS></PISAliq></PIS><COFINS><COFINSAliq><CST>01</CST><vBC>64.64</vBC><pCOFINS>7.6000</pCOFINS><vCOFINS>4.91</vCOFINS></COFINSAliq></COFINS></imposto><infAdProd>ICMS ST Recolhido antecipadamente pelo Fabricante.</infAdProd></det><det nItem="8"><prod><cProd>E00007236</cProd><cEAN>7896588955039</cEAN><xProd>DOGLIC BISC COMBO PROMO 3 SAB 12X500G</xProd><NCM>23091000</NCM><CEST>2200100</CEST><CFOP>5405</CFOP><uCom>CX</uCom><qCom>1.0000</qCom><vUnCom>100.9500000000</vUnCom><vProd>100.95</vProd><cEANTrib>07896588955039</cEANTrib><uTrib>CX</uTrib><qTrib>1.0000</qTrib><vUnTrib>100.9500000000</vUnTrib><vFrete>1.55</vFrete><indTot>1</indTot><xPed>2954347</xPed></prod><imposto><ICMS><ICMS60><orig>0</orig><CST>60</CST><vBCSTRet>99.52</vBCSTRet><pST>20.0000</pST><vICMSSubstituto>12.27</vICMSSubstituto><vICMSSTRet>5.64</vICMSSTRet><vBCFCPSTRet>99.52</vBCFCPSTRet><pFCPSTRet>2.0000</pFCPSTRet><vFCPSTRet>1.99</vFCPSTRet></ICMS60></ICMS><IPI><cEnq>999</cEnq><IPITrib><CST>99</CST><vBC>0.00</vBC><pIPI>0.0000</pIPI><vIPI>0.00</vIPI></IPITrib></IPI><PIS><PISAliq><CST>01</CST><vBC>102.50</vBC><pPIS>1.6500</pPIS><vPIS>1.69</vPIS></PISAliq></PIS><COFINS><COFINSAliq><CST>01</CST><vBC>102.50</vBC><pCOFINS>7.6000</pCOFINS><vCOFINS>7.79</vCOFINS></COFINSAliq></COFINS></imposto><infAdProd>ICMS ST Recolhido antecipadamente pelo Fabricante.</infAdProd></det><det nItem="9"><prod><cProd>E00013537</cProd><cEAN>7896588943258</cEAN><xProd>EQ FREEZE DRIED SNACK CALM 8X30G</xProd><NCM>23091000</NCM><CEST>2200100</CEST><CFOP>5405</CFOP><uCom>CX</uCom><qCom>1.0000</qCom><vUnCom>60.3200000000</vUnCom><vProd>60.32</vProd><cEANTrib>07896588943258</cEANTrib><uTrib>CX</uTrib><qTrib>1.0000</qTrib><vUnTrib>60.3200000000</vUnTrib><vFrete>0.15</vFrete><indTot>1</indTot><xPed>2954347</xPed></prod><imposto><ICMS><ICMS60><orig>0</orig><CST>60</CST><vBCSTRet>139.23</vBCSTRet><pST>20.0000</pST><vICMSSubstituto>17.16</vICMSSubstituto><vICMSSTRet>7.90</vICMSSTRet><vBCFCPSTRet>139.23</vBCFCPSTRet><pFCPSTRet>2.0000</pFCPSTRet><vFCPSTRet>2.78</vFCPSTRet></ICMS60></ICMS><IPI><cEnq>999</cEnq><IPITrib><CST>99</CST><vBC>0.00</vBC><pIPI>0.0000</pIPI><vIPI>0.00</vIPI></IPITrib></IPI><PIS><PISAliq><CST>01</CST><vBC>60.47</vBC><pPIS>1.6500</pPIS><vPIS>1.00</vPIS></PISAliq></PIS><COFINS><COFINSAliq><CST>01</CST><vBC>60.47</vBC><pCOFINS>7.6000</pCOFINS><vCOFINS>4.60</vCOFINS></COFINSAliq></COFINS></imposto><infAdProd>ICMS ST Recolhido antecipadamente pelo Fabricante.</infAdProd></det><det nItem="10"><prod><cProd>E00005697</cProd><cEAN>7896588942701</cEAN><xProd>EQ SNACK SAUDE ORAL RP 8X80G</xProd><NCM>23091000</NCM><CEST>2200100</CEST><CFOP>5405</CFOP><uCom>CX</uCom><qCom>1.0000</qCom><vUnCom>60.3400000000</vUnCom><vProd>60.34</vProd><cEANTrib>07896588942701</cEANTrib><uTrib>CX</uTrib><qTrib>1.0000</qTrib><vUnTrib>60.3400000000</vUnTrib><vFrete>0.20</vFrete><indTot>1</indTot><xPed>2954347</xPed></prod><imposto><ICMS><ICMS60><orig>0</orig><CST>60</CST><vBCSTRet>35.65</vBCSTRet><pST>20.0000</pST><vICMSSubstituto>4.39</vICMSSubstituto><vICMSSTRet>2.02</vICMSSTRet><vBCFCPSTRet>35.65</vBCFCPSTRet><pFCPSTRet>2.0000</pFCPSTRet><vFCPSTRet>0.71</vFCPSTRet></ICMS60></ICMS><IPI><cEnq>999</cEnq><IPITrib><CST>99</CST><vBC>0.00</vBC><pIPI>0.0000</pIPI><vIPI>0.00</vIPI></IPITrib></IPI><PIS><PISAliq><CST>01</CST><vBC>60.54</vBC><pPIS>1.6500</pPIS><vPIS>1.00</vPIS></PISAliq></PIS><COFINS><COFINSAliq><CST>01</CST><vBC>60.54</vBC><pCOFINS>7.6000</pCOFINS><vCOFINS>4.60</vCOFINS></COFINSAliq></COFINS></imposto><infAdProd>ICMS ST Recolhido antecipadamente pelo Fabricante.</infAdProd></det><total><ICMSTot><vBC>0.00</vBC><vICMS>0.00</vICMS><vICMSDeson>0.00</vICMSDeson><vFCP>0.00</vFCP><vBCST>0.00</vBCST><vST>0.00</vST><vFCPST>0.00</vFCPST><vFCPSTRet>35.71</vFCPSTRet><vProd>1648.05</vProd><vFrete>42.58</vFrete><vSeg>0.00</vSeg><vDesc>0.00</vDesc><vII>0.00</vII><vIPI>0.00</vIPI><vIPIDevol>0.00</vIPIDevol><vPIS>27.89</vPIS><vCOFINS>128.48</vCOFINS><vOutro>0.00</vOutro><vNF>1690.63</vNF></ICMSTot></total><transp><modFrete>0</modFrete><transporta><CPF>00118128698</CPF><xNome>ADEVALDO PEREIRA DE OLIVEIRA</xNome><xEnder>RUA QUARENTA E UM 206</xEnder><xMun>CONTAGEM</xMun><UF>MG</UF></transporta><vol><qVol>20</qVol><pesoL>183.320</pesoL><pesoB>187.501</pesoB></vol></transp><cobr><fat><nFat>0095076150</nFat><vOrig>1690.63</vOrig><vDesc>0.00</vDesc><vLiq>1690.63</vLiq></fat><dup><nDup>001</nDup><dVenc>2019-06-11</dVenc><vDup>422.66</vDup></dup><dup><nDup>002</nDup><dVenc>2019-06-18</dVenc><vDup>422.66</vDup></dup><dup><nDup>003</nDup><dVenc>2019-06-25</dVenc><vDup>422.66</vDup></dup><dup><nDup>004</nDup><dVenc>2019-07-02</dVenc><vDup>422.65</vDup></dup></cobr><pag><detPag><tPag>15</tPag><vPag>1690.63</vPag></detPag></pag><infAdic><infAdFisco>IMPOSTO RETIDO POR SUBST. TRIB. NOS TERMOS DO PROT. 26/2004 DE 25/06/04 - ICMS S.T. RETIDO: BC R$ 1.786,61 VALOR ICMS R$ 101,32. PRAZO DE VALIDADE DE 07 DIAS IMPRORROGAVEL. REGIME ESPECIAL PTA 16.000225179-22 - DF/BETIM. SERVICO DE TRANSPORTES ISENTO DE ICMS DE ACORDO COM ART. 6o PARTE 1 ANEXO I, ITEM 144 RICMS/MG.</infAdFisco><infCpl>Representante: 507033. Pedido: 2954347. FUNDO DE ERRADICACAO DA MISERIA RECOLHIDO PELO FABRICANTE. Valor FCP:R$0,00; VALOR FCP ST: R$35,71</infCpl></infAdic></infNFe><Signature xmlns="http://www.w3.org/2000/09/xmldsig#"><SignedInfo><CanonicalizationMethod Algorithm="http://www.w3.org/TR/2001/REC-xml-c14n-20010315" /><SignatureMethod Algorithm="http://www.w3.org/2000/09/xmldsig#rsa-sha1" /><Reference URI="#NFe31190607489678000129550010001358331762995330"><Transforms><Transform Algorithm="http://www.w3.org/2000/09/xmldsig#enveloped-signature" /><Transform Algorithm="http://www.w3.org/TR/2001/REC-xml-c14n-20010315" /></Transforms><DigestMethod Algorithm="http://www.w3.org/2000/09/xmldsig#sha1" /><DigestValue>o4gkLWz/ct8s43u4A8bVo4gLe2A=</DigestValue></Reference></SignedInfo><SignatureValue>aTfAtLGjFpObItA3WUpg91JsVIUVoAFAr3qpEsFs2ww8ySP/+nPEor0U7RjSFHsnkYO5sKAs2uLf
dvKZ/JyVMNDuLcYrADggV7dfD/1FIDs016ZqIjNk4SYweRhPd7KjJwzTUHdth3JlHCqv9HV0H13v
IGZb24CE7eVFAHF8q/ZHim943VLDG2Zs2CXJVEq9N99EEa8fSNAWBHG5GhyPJerWb4Z+/s8VZ9yN
5V3I1oLbwnh9D7pLW5hWtZvgPqYpsD92RY7gT+F91TjUkGfXtSC4hoyKglN1j8EJcxEbhCM+XaLf
czbTWPJLOq7HgogLENxb0O+OUep5H58d5+v+2A==</SignatureValue><KeyInfo><X509Data><X509Certificate>MIIHqTCCBZGgAwIBAgIICBe7fSJ8WZ8wDQYJKoZIhvcNAQELBQAwTDELMAkGA1UEBhMCQlIxEzAR
BgNVBAoMCklDUC1CcmFzaWwxKDAmBgNVBAMMH1NFUkFTQSBDZXJ0aWZpY2Fkb3JhIERpZ2l0YWwg
djUwHhcNMTkwNTEwMTk1MTAwWhcNMjAwNTA5MTk1MTAwWjCB/DELMAkGA1UEBhMCQlIxEzARBgNV
BAoMCklDUC1CcmFzaWwxFDASBgNVBAsMCyhFTSBCUkFOQ08pMRgwFgYDVQQLDA8wMDAwMDEwMDkw
MjIzMjAxFDASBgNVBAsMCyhFTSBCUkFOQ08pMRQwEgYDVQQLDAsoRU0gQlJBTkNPKTEoMCYGA1UE
CwwfU0VSQVNBIENlcnRpZmljYWRvcmEgRGlnaXRhbCB2NTEXMBUGA1UECwwONjIxNzM2MjAwMDg2
NzkxFDASBgNVBAsMCyhFTSBCUkFOQ08pMSMwIQYDVQQDDBpTVUwgTUlORUlSQSBBTElNRU5UT1Mg
TFREQTCCASIwDQYJKoZIhvcNAQEBBQADggEPADCCAQoCggEBAJywn0M4itQmrc5X335xqqAinX9L
HG4LtFJ+cTpRUX+DvmMO+frKPVIzUllEWBrcJuucditrdRsFnGWcSVP8ZTPQqNxsSGusSqDrgOqb
NJmq/GyRzut2LxNSKtxkmhGzjlTY7ycNvjES11s2f4Y99tqeJfij3BvJcjnjCoS285IC4KbtBqq2
4wVEHjGTu5E7jrcmjklY4kc+TiO/XuIMsiErj3EjOJ3KyX6oT1KRvnHue+oOwx155mMASbsNbOPq
4X2lP2wJqVj5gBeLbSIvoupZiqTtFf0mz3Ry4CJ3kLtqJJism3waVyEWGCLzzQhPT/ImUPPufoXM
XKDstmkJYzUCAwEAAaOCAtwwggLYMB8GA1UdIwQYMBaAFFZ1r0pzstgIxH37bCgcEdX3wajMMIGX
BggrBgEFBQcBAQSBijCBhzBHBggrBgEFBQcwAoY7aHR0cDovL3d3dy5jZXJ0aWZpY2Fkb2RpZ2l0
YWwuY29tLmJyL2NhZGVpYXMvc2VyYXNhY2R2NS5wN2IwPAYIKwYBBQUHMAGGMGh0dHA6Ly9vY3Nw
LmNlcnRpZmljYWRvZGlnaXRhbC5jb20uYnIvc2VyYXNhY2R2NTCBuwYDVR0RBIGzMIGwgRlQQVJB
U09DSUVUQVJJT0NTQUBBRE0uQ09NoD4GBWBMAQMEoDUTMzA0MDMxOTc2MjYwNjUwNjU4ODkwMDAw
MDAwMDAwMDAwMDAwMDI1NjQyNzk2M1NTUCBTUKAfBgVgTAEDAqAWExRNQVJDRUxPIEtFTkpJIEFP
WUFHSaAZBgVgTAEDA6AQEw4wNzQ4OTY3ODAwMDEyOaAXBgVgTAEDB6AOEwwwMDAwMDAwMDAwMDAw
cQYDVR0gBGowaDBmBgZgTAECAQYwXDBaBggrBgEFBQcCARZOaHR0cDovL3B1YmxpY2FjYW8uY2Vy
dGlmaWNhZG9kaWdpdGFsLmNvbS5ici9yZXBvc2l0b3Jpby9kcGMvZGVjbGFyYWNhby1zY2QucGRm
MB0GA1UdJQQWMBQGCCsGAQUFBwMCBggrBgEFBQcDBDCBmwYDVR0fBIGTMIGQMEmgR6BFhkNodHRw
Oi8vd3d3LmNlcnRpZmljYWRvZGlnaXRhbC5jb20uYnIvcmVwb3NpdG9yaW8vbGNyL3NlcmFzYWNk
djUuY3JsMEOgQaA/hj1odHRwOi8vbGNyLmNlcnRpZmljYWRvcy5jb20uYnIvcmVwb3NpdG9yaW8v
bGNyL3NlcmFzYWNkdjUuY3JsMB0GA1UdDgQWBBQLF7p64CIfPa/xre+grN4XgJfczTAOBgNVHQ8B
Af8EBAMCBeAwDQYJKoZIhvcNAQELBQADggIBACE6mLkbC4Zf9NdI5hjPCIjnfImyPsfQyemFY5ZS
1osTVRr5tZxlFTtQxRvRy5ttZpGzH+mgC3djkPlj0s8HeahVzKQPC+QvSEZ7xF+vCbqygozao6QD
Il3iUdbXGVKCbG2TW9fQxSZSXDykYWYbd0UvklaCGVBsMNQx1wq2NxpCeVuyGoqPmtKpva58GQ9T
/+6r+36yp3H0xBH0f78QEkVClsDzSu4LLcHE/bJNpECnqz/xWWQusrxKtwk7iih/NQooK4fruUjF
+iGoJMPRF87dcU1wdYxivrSWdL+JIDgusWSa9+CfLsFm05194oep0O23Cws0JBSd4seVsvHJ9j+9
xtmKrwlXhDWvJqRFlRqCO99QIfRwlnCClKwa/cDWftSQhBpxZNF5GtVf09dn7uxFjnOstqXXzZea
ePeLBOmib/ZvjuNVGONOnTXSaciDF4XNtTKGgcjbdo84WLykWSEiqasQ5K5ctf8IhYCGjkp0XlL6
u34qWLIawhuQ5MmVd9R7EodtgvGPqVwH65BUjwdw4es2zVOz2744o03X4Ld7F0KTms0lgUUNWV0v
MG+XZGZDUCOna7NVdLaXs+mi3TKA3M2Qo8c7KMjJYPk7KGRAN6li+Cq1SVTGCqrpgKzvyqZW5oUr
CrIiLEGG1D8ol5G3J92vLc09UsjgIPL5CH14</X509Certificate></X509Data></KeyInfo></Signature></NFe><protNFe versao="4.00"><infProt Id="ID131193311986245">
  <tpAmb>1</tpAmb>
  <verAplic>14.3.7</verAplic>
  <chNFe>31190607489678000129550010001358331762995330</chNFe>
  <dhRecbto>2019-06-04T09:05:25-03:00</dhRecbto>
  <nProt>131193311986245</nProt>
  <digVal>o4gkLWz/ct8s43u4A8bVo4gLe2A=</digVal>
  <cStat>100</cStat>
  <xMotivo>Autorizado o uso da NF-e</xMotivo>
</infProt></protNFe></nfeProc>
