<?xml version="1.0" encoding="UTF-8"?><nfeProc versao="4.00" xmlns="http://www.portalfiscal.inf.br/nfe"><NFe xmlns="http://www.portalfiscal.inf.br/nfe"><infNFe versao="4.00" Id="NFe31190109119144000136550010000037851026421891"><ide><cUF>31</cUF><cNF>02642189</cNF><natOp>VENDA</natOp><mod>55</mod><serie>1</serie><nNF>3785</nNF><dhEmi>2019-01-14T08:36:22-02:00</dhEmi><dhSaiEnt>2019-01-14T08:36:22-02:00</dhSaiEnt><tpNF>1</tpNF><idDest>1</idDest><cMunFG>3106200</cMunFG><tpImp>1</tpImp><tpEmis>1</tpEmis><cDV>1</cDV><tpAmb>1</tpAmb><finNFe>1</finNFe><indFinal>0</indFinal><indPres>2</indPres><procEmi>0</procEmi><verProc>3.0</verProc></ide><emit><CNPJ>09119144000136</CNPJ><xNome>FIXAR COMERCIO DE PARAFUSOS E FERRAMENTAS LTDA ME</xNome><xFant>FIXAR COMERCIO DE PARAFUSOS E FERRAMENTAS</xFant><enderEmit><xLgr>Rua Pio IX</xLgr><nro>940</nro><xBairro>BETIM INDUSTRIAL</xBairro><cMun>3106705</cMun><xMun>BETIM</xMun><UF>MG</UF><CEP>32670448</CEP><cPais>1058</cPais><xPais>BRASIL</xPais><fone>3135923110</fone></enderEmit><IE>0010453960081</IE><CRT>1</CRT></emit><dest><CNPJ>18739250000103</CNPJ><xNome>USINTEQ USINAGEM TECNICA QUELUZ LTDA</xNome><enderDest><xLgr>RUA LOPES FRANCO</xLgr><nro>610</nro><xBairro>CARIJOS</xBairro><cMun>3118304</cMun><xMun>CONSELHEIRO LAFAIETE</xMun><UF>MG</UF><CEP>36400000</CEP><cPais>1058</cPais><xPais>BRASIL</xPais><fone>3187266622</fone></enderDest><indIEDest>1</indIEDest><IE>1831698490065</IE></dest><det nItem="1"><prod><cProd>1470</cProd><cEAN/><xProd>Tucho p/ Prisioneiro Carcaca M8 x 14 x 1,5 x 25</xProd><NCM>87089990</NCM><CFOP>5102</CFOP><uCom>PECA</uCom><qCom>100.0000</qCom><vUnCom>2.0000000000</vUnCom><vProd>200.00</vProd><cEANTrib/><uTrib>PECA</uTrib><qTrib>100.0000</qTrib><vUnTrib>2.0000000000</vUnTrib><indTot>1</indTot></prod><imposto><ICMS><ICMSSN101><orig>0</orig><CSOSN>101</CSOSN><pCredSN>0.0000</pCredSN><vCredICMSSN>0.00</vCredICMSSN></ICMSSN101></ICMS><PIS><PISNT><CST>04</CST></PISNT></PIS><COFINS><COFINSNT><CST>04</CST></COFINSNT></COFINS></imposto></det><det nItem="2"><prod><cProd>1468</cProd><cEAN/><xProd>Tucho Carcaca p/ Prisioneiro 8 x 10 x 20</xProd><NCM>87089990</NCM><CFOP>5102</CFOP><uCom>PC</uCom><qCom>100.0000</qCom><vUnCom>1.6000000000</vUnCom><vProd>160.00</vProd><cEANTrib/><uTrib>PC</uTrib><qTrib>100.0000</qTrib><vUnTrib>1.6000000000</vUnTrib><indTot>1</indTot></prod><imposto><ICMS><ICMSSN101><orig>0</orig><CSOSN>101</CSOSN><pCredSN>0.0000</pCredSN><vCredICMSSN>0.00</vCredICMSSN></ICMSSN101></ICMS><PIS><PISNT><CST>04</CST></PISNT></PIS><COFINS><COFINSNT><CST>04</CST></COFINSNT></COFINS></imposto></det><det nItem="3"><prod><cProd>1669</cProd><cEAN/><xProd>DISCO CORTE INOX 4.1/2 DISFLEX</xProd><NCM>68042211</NCM><CFOP>5403</CFOP><uCom>UN</uCom><qCom>20.0000</qCom><vUnCom>2.9900000000</vUnCom><vProd>59.80</vProd><cEANTrib/><uTrib>UN</uTrib><qTrib>20.0000</qTrib><vUnTrib>2.9900000000</vUnTrib><indTot>1</indTot></prod><imposto><ICMS><ICMSSN500><orig>0</orig><CSOSN>500</CSOSN><vBCSTRet>59.80</vBCSTRet><pST>0.0000</pST><vICMSSTRet>0.00</vICMSSTRet></ICMSSN500></ICMS><PIS><PISNT><CST>04</CST></PISNT></PIS><COFINS><COFINSNT><CST>04</CST></COFINSNT></COFINS></imposto></det><det nItem="4"><prod><cProd>206</cProd><cEAN/><xProd>PF. Sext. 8.8 M10 x 50</xProd><NCM>73181500</NCM><CFOP>5102</CFOP><uCom>PECA</uCom><qCom>50.0000</qCom><vUnCom>1.0000000000</vUnCom><vProd>50.00</vProd><cEANTrib/><uTrib>PECA</uTrib><qTrib>50.0000</qTrib><vUnTrib>1.0000000000</vUnTrib><indTot>1</indTot></prod><imposto><ICMS><ICMSSN101><orig>0</orig><CSOSN>101</CSOSN><pCredSN>0.0000</pCredSN><vCredICMSSN>0.00</vCredICMSSN></ICMSSN101></ICMS><PIS><PISNT><CST>04</CST></PISNT></PIS><COFINS><COFINSNT><CST>04</CST></COFINSNT></COFINS></imposto><infAdProd>Parafuso Cabeca Sextavada 8.8 M10 x 50</infAdProd></det><det nItem="5"><prod><cProd>187</cProd><cEAN/><xProd>PF. Sext. 8.8 M8 x 50</xProd><NCM>73181500</NCM><CFOP>5403</CFOP><uCom>PC</uCom><qCom>50.0000</qCom><vUnCom>0.8000000000</vUnCom><vProd>40.00</vProd><cEANTrib/><uTrib>PC</uTrib><qTrib>50.0000</qTrib><vUnTrib>0.8000000000</vUnTrib><indTot>1</indTot></prod><imposto><ICMS><ICMSSN500><orig>0</orig><CSOSN>500</CSOSN><vBCSTRet>40.00</vBCSTRet><pST>0.0000</pST><vICMSSTRet>0.00</vICMSSTRet></ICMSSN500></ICMS><PIS><PISNT><CST>04</CST></PISNT></PIS><COFINS><COFINSNT><CST>04</CST></COFINSNT></COFINS></imposto><infAdProd>Parafuso Cabeca Sext 8.8 M8 x 50</infAdProd></det><total><ICMSTot><vBC>0.00</vBC><vICMS>0.00</vICMS><vICMSDeson>0.00</vICMSDeson><vFCP>0.00</vFCP><vBCST>0.00</vBCST><vST>0.00</vST><vFCPST>0.00</vFCPST><vFCPSTRet>0.00</vFCPSTRet><vProd>509.80</vProd><vFrete>0.00</vFrete><vSeg>0.00</vSeg><vDesc>0.00</vDesc><vII>0.00</vII><vIPI>0.00</vIPI><vIPIDevol>0.00</vIPIDevol><vPIS>0.00</vPIS><vCOFINS>0.00</vCOFINS><vOutro>0.00</vOutro><vNF>509.80</vNF></ICMSTot></total><transp><modFrete>1</modFrete><retTransp><vServ>0.00</vServ><vBCRet>0.00</vBCRet><pICMSRet>0.00</pICMSRet><vICMSRet>0.00</vICMSRet><CFOP>5353</CFOP><cMunFG>3118304</cMunFG></retTransp><vol><qVol>1</qVol><esp>CX</esp><pesoL>6.000</pesoL><pesoB>6.000</pesoB></vol></transp><pag><detPag><tPag>01</tPag><vPag>509.80</vPag></detPag></pag><infAdic><infCpl>BOLETO 28DDFRETE FOB AGILEMPRESA OPTANTE PELO SIMPLES NACIONAL. PERMITE APROVEITAMENTO DE CREDITO DE ICMS NO VALOR DE R$7,63, CORRESPONDENTE A ALIQUOTA DE 1,86%, NOS TERMOS DO ARTIGO 123 DA LEI COMPLEMENTAR.</infCpl></infAdic></infNFe><Signature xmlns="http://www.w3.org/2000/09/xmldsig#"><SignedInfo><CanonicalizationMethod Algorithm="http://www.w3.org/TR/2001/REC-xml-c14n-20010315" /><SignatureMethod Algorithm="http://www.w3.org/2000/09/xmldsig#rsa-sha1" /><Reference URI="#NFe31190109119144000136550010000037851026421891"><Transforms><Transform Algorithm="http://www.w3.org/2000/09/xmldsig#enveloped-signature" /><Transform Algorithm="http://www.w3.org/TR/2001/REC-xml-c14n-20010315" /></Transforms><DigestMethod Algorithm="http://www.w3.org/2000/09/xmldsig#sha1" /><DigestValue>Aa57Jm1jvs7uYo0GicZTzg+nmSk=</DigestValue></Reference></SignedInfo><SignatureValue>u2KVdxViapBM9JkeZ53ldWFxAGEXUTuF7qPYbm9jFTN3LGr4DLCbDyw2b+83jj04EEBGoz1t9aCdqFgqgf9IrfvpFVay7LFSSzvCWNwhI0gwib/nrEeQKo7Ggii1Ri6DyKTWaUJoSdtfXL71IZcsa7c9qCfI/wtuyqmbkxL6SSc=</SignatureValue><KeyInfo><X509Data><X509Certificate>MIICOTCCAaKgAwIBAgIQJpLn3fwH17RNXJHw5VenaDANBgkqhkiG9w0BAQUFADBbMVkwVwYDVQQDHlAAdwB3AHcALgBmAHMAaQBzAHQALgBjAG8AbQAuAGIAcgAgACgAUwBFAE0AIABWAEEATABJAEQAQQBEAEUAIABKAFUAUgDNAEQASQBDAEEAKTAeFw0xNTEyMjQwODI1MjVaFw0xODEyMjQwODI1MjVaMFsxWTBXBgNVBAMeUAB3AHcAdwAuAGYAcwBpAHMAdAAuAGMAbwBtAC4AYgByACAAKABTAEUATQAgAFYAQQBMAEkARABBAEQARQAgAEoAVQBSAM0ARABJAEMAQQApMIGfMA0GCSqGSIb3DQEBAQUAA4GNADCBiQKBgQDX4BYmJiNwrPz9At2ioXYkMuMWAOf669VPS3SAzIKkJLhSE7Bf9sbTjGHRFZhs6STxKkMBKKnx6dqAEMGlQwDSU42/kqhGya28SUn3HigH2w3dR/536Gt4eAxyLp9ODNXUqWTpnraWCeT41kcnJ27cmOAUMxzxDcsA93n32L4u8wIDAQABMA0GCSqGSIb3DQEBBQUAA4GBAAN89zf+wSFL+4+2Ic8mGva8Z51EzYzNgYEqXwEMHxw4jCxxbsuxewQWedSGWi3SFZla6zmNUEA+UO95tSZ353klTvWDzut2BFSJOPLcMu8HPTTdnMt4ofVeVqKyi2vp+3t78vjqDAAfSAu5C9wT7stoUx41Nok+L6WbmpOIgvHy</X509Certificate></X509Data></KeyInfo></Signature></NFe><protNFe versao="4.00"><infProt><tpAmb>1</tpAmb><verAplic>3.0</verAplic><chNFe>31190109119144000136550010000037851026421891</chNFe><dhRecbto>2019-01-14T08:36:25-02:00</dhRecbto><nProt>131193171429479</nProt><digVal>wjyU0eIpHslmwr3gRy3wFsAXtlo=</digVal><cStat>100</cStat><xMotivo>Autorizado o uso da NF-e</xMotivo></infProt></protNFe></nfeProc>
