<nfeProc versao="4.00" xmlns="http://www.portalfiscal.inf.br/nfe"><NFe xmlns="http://www.portalfiscal.inf.br/nfe"><infNFe Id="NFe31210760409075020340550010011847691058250939" versao="4.00"><ide><cUF>31</cUF><cNF>05825093</cNF><natOp>VDA.MERC.SUJEITA AO REG.DE ST / VD.MERC.SUJEITA AO REG.DE S</natOp><mod>55</mod><serie>1</serie><nNF>1184769</nNF><dhEmi>2021-07-31T09:52:31-03:00</dhEmi><dhSaiEnt>2021-07-31T09:57:30-03:00</dhSaiEnt><tpNF>1</tpNF><idDest>1</idDest><cMunFG>3105608</cMunFG><tpImp>2</tpImp><tpEmis>1</tpEmis><cDV>9</cDV><tpAmb>1</tpAmb><finNFe>1</finNFe><indFinal>0</indFinal><indPres>2</indPres><procEmi>0</procEmi><verProc>SAP GRC NFE 4.00</verProc></ide><emit><CNPJ>60409075020340</CNPJ><xNome>Nestle Brasil Ltda</xNome><xFant>BR DC Broker Barbacena</xFant><enderEmit><xLgr>Av Helena Aguiar de Figueiredo</xLgr><nro>407</nro><xCpl>GP B SL1</xCpl><xBairro>Ipanema</xBairro><cMun>3105608</cMun><xMun>Barbacena</xMun><UF>MG</UF><CEP>36205507</CEP><xPais>Brasil</xPais><fone>08000304321</fone></enderEmit><IE>0017611430149</IE><IM>109203</IM><CRT>3</CRT></emit><dest><CNPJ>23809403000181</CNPJ><xNome>Mercearia Serfons Ltda</xNome><enderDest><xLgr>R Santa Apodonia</xLgr><nro>116</nro><xBairro>Fonte Grande</xBairro><cMun>3118304</cMun><xMun>Conselheiro Lafaiete</xMun><UF>MG</UF><CEP>36400000</CEP><cPais>1058</cPais><xPais>Brasil</xPais><fone>3137623187</fone></enderDest><indIEDest>1</indIEDest><IE>1835569290071</IE></dest><autXML><CNPJ>19417473000117</CNPJ></autXML><det nItem="1"><prod><cProd>000000000012131235</cProd><cEAN>7891000023808</cEAN><xProd>NEGRESCO Biscoito Recheado 63x140g BR</xProd><NCM>19053100</NCM><CEST>1705300</CEST><indEscala>S</indEscala><CFOP>5403</CFOP><uCom>UNI</uCom><qCom>9.0000</qCom><vUnCom>1.9088888889</vUnCom><vProd>17.18</vProd><cEANTrib>7891000023808</cEANTrib><uTrib>UNI</uTrib><qTrib>9.0000</qTrib><vUnTrib>1.9088888889</vUnTrib><indTot>1</indTot><xPed>2492017</xPed><nItemPed>000010</nItemPed><nFCI>8921E08B-1C82-41C0-8D67-01266D14F222</nFCI></prod><imposto><ICMS><ICMS10><orig>5</orig><CST>10</CST><modBC>3</modBC><vBC>17.18</vBC><pICMS>18.0000</pICMS><vICMS>3.09</vICMS><modBCST>4</modBCST><pMVAST>35.0000</pMVAST><vBCST>23.19</vBCST><pICMSST>18.0000</pICMSST><vICMSST>1.08</vICMSST></ICMS10></ICMS><IPI><cEnq>999</cEnq><IPINT><CST>51</CST></IPINT></IPI><PIS><PISAliq><CST>01</CST><vBC>17.18</vBC><pPIS>1.6500</pPIS><vPIS>0.28</vPIS></PISAliq></PIS><COFINS><COFINSAliq><CST>01</CST><vBC>17.18</vBC><pCOFINS>7.6000</pCOFINS><vCOFINS>1.31</vCOFINS></COFINSAliq></COFINS></imposto><infAdProd>Resolucao do Senado Federal no 13/12,No da FCI 8921E08B-1C82-41C0-8D67-01266D14F222</infAdProd></det><det nItem="2"><prod><cProd>000000000012325231</cProd><cEAN>7891000241356</cEAN><xProd>PASSATEMPO Bisc Recheado Choc 70x130g BR</xProd><NCM>19053100</NCM><CEST>1705300</CEST><indEscala>S</indEscala><CFOP>5403</CFOP><uCom>UNI</uCom><qCom>20.0000</qCom><vUnCom>1.5775000000</vUnCom><vProd>31.55</vProd><cEANTrib>7891000241356</cEANTrib><uTrib>UNI</uTrib><qTrib>20.0000</qTrib><vUnTrib>1.5775000000</vUnTrib><indTot>1</indTot><xPed>2492017</xPed><nItemPed>000020</nItemPed><nFCI>01232346-514C-4DD9-BA34-E3BE94AA2CAB</nFCI></prod><imposto><ICMS><ICMS10><orig>5</orig><CST>10</CST><modBC>3</modBC><vBC>31.55</vBC><pICMS>18.0000</pICMS><vICMS>5.68</vICMS><modBCST>4</modBCST><pMVAST>35.0000</pMVAST><vBCST>42.59</vBCST><pICMSST>18.0000</pICMSST><vICMSST>1.99</vICMSST></ICMS10></ICMS><IPI><cEnq>999</cEnq><IPINT><CST>51</CST></IPINT></IPI><PIS><PISAliq><CST>01</CST><vBC>31.55</vBC><pPIS>1.6500</pPIS><vPIS>0.52</vPIS></PISAliq></PIS><COFINS><COFINSAliq><CST>01</CST><vBC>31.55</vBC><pCOFINS>7.6000</pCOFINS><vCOFINS>2.40</vCOFINS></COFINSAliq></COFINS></imposto><infAdProd>Resolucao do Senado Federal no 13/12,No da FCI 01232346-514C-4DD9-BA34-E3BE94AA2CAB</infAdProd></det><det nItem="3"><prod><cProd>000000000012342557</cProd><cEAN>7891000248775</cEAN><xProd>KIT KAT 4Fngr Leite 4(24x41.5g) BR</xProd><NCM>19053200</NCM><CEST>1705800</CEST><indEscala>S</indEscala><CFOP>5405</CFOP><uCom>EXB</uCom><qCom>1.0000</qCom><vUnCom>50.4600000000</vUnCom><vProd>50.46</vProd><cEANTrib>7891000248768</cEANTrib><uTrib>UNI</uTrib><qTrib>24.0000</qTrib><vUnTrib>2.1025000000</vUnTrib><indTot>1</indTot><xPed>2492017</xPed><nItemPed>000030</nItemPed><nFCI>036EAD6E-96A7-4467-8A74-A49E4FB9C5AA</nFCI></prod><imposto><ICMS><ICMS60><orig>5</orig><CST>60</CST><vBCSTRet>32.94</vBCSTRet><pST>18.0000</pST><vICMSSubstituto>2.73</vICMSSubstituto><vICMSSTRet>3.20</vICMSSTRet></ICMS60></ICMS><IPI><cEnq>999</cEnq><IPINT><CST>51</CST></IPINT></IPI><PIS><PISAliq><CST>01</CST><vBC>50.46</vBC><pPIS>1.6500</pPIS><vPIS>0.83</vPIS></PISAliq></PIS><COFINS><COFINSAliq><CST>01</CST><vBC>50.46</vBC><pCOFINS>7.6000</pCOFINS><vCOFINS>3.83</vCOFINS></COFINSAliq></COFINS></imposto><infAdProd>Resolucao do Senado Federal no 13/12,No da FCI 036EAD6E-96A7-4467-8A74-A49E4FB9C5AAValor da BC do ICMS ST retido: 32,94 , Valor do ICMS ST retido: 3,20</infAdProd></det><total><ICMSTot><vBC>48.73</vBC><vICMS>8.77</vICMS><vICMSDeson>0.00</vICMSDeson><vFCP>0.00</vFCP><vBCST>65.78</vBCST><vST>3.07</vST><vFCPST>0.00</vFCPST><vFCPSTRet>0.00</vFCPSTRet><vProd>99.19</vProd><vFrete>0.00</vFrete><vSeg>0.00</vSeg><vDesc>0.00</vDesc><vII>0.00</vII><vIPI>0.00</vIPI><vIPIDevol>0.00</vIPIDevol><vPIS>1.63</vPIS><vCOFINS>7.54</vCOFINS><vOutro>0.00</vOutro><vNF>102.26</vNF></ICMSTot></total><transp><modFrete>0</modFrete><transporta><CNPJ>14635653000151</CNPJ><xNome>Brocker Atos Distribuicao Ltda</xNome><IE>0018741160061</IE><xEnder>Av Helena Aguiar de 407 Gp B Sl 02</xEnder><xMun>Barbacena</xMun><UF>MG</UF></transporta><vol><qVol>30</qVol><esp>Diversos</esp><pesoL>4.856</pesoL><pesoB>4.950</pesoB></vol></transp><cobr><fat><nFat>9641009952</nFat><vOrig>102.26</vOrig><vDesc>0.00</vDesc><vLiq>102.26</vLiq></fat><dup><nDup>001</nDup><dVenc>2021-08-23</dVenc><vDup>102.26</vDup></dup></cobr><pag><detPag><tPag>15</tPag><vPag>102.26</vPag></detPag></pag><infAdic><infAdFisco>Valor da BC do ICMS ST retido: 32,94 , Valor do ICMS ST retido: 3,20</infAdFisco><infCpl>Docnum: 0174116880 Cli: 0002970557 FFt: 6617 Emp: BR10 Org. Vendas: BRL1 / 06 / 00 Fvd: Remessa: 8384946997 Doct.Fat: 9641009952 N. Carga: 8025772025 Parceiro 10509535 Pedido: 5393335138 *Boleto Anexo* Tax Perm 72.0000000 PedCli: 2492017Vol(M3): 0.002Valor L quido: 102,26Total da BC do ICMS ST retido: 32,94 Total do ICMS ST retido: 3,20Sujeito a ICMS e Sub.Trib.ICMS j pago via Sub.Trib.</infCpl><obsCont xCampo="FATURA"><xTexto>CondPagto Vencto 21 dias apos dtfat Venc 230821</xTexto></obsCont></infAdic></infNFe><Signature xmlns="http://www.w3.org/2000/09/xmldsig#"><SignedInfo><CanonicalizationMethod Algorithm="http://www.w3.org/TR/2001/REC-xml-c14n-20010315" /><SignatureMethod Algorithm="http://www.w3.org/2000/09/xmldsig#rsa-sha1" /><Reference URI="#NFe31210760409075020340550010011847691058250939"><Transforms><Transform Algorithm="http://www.w3.org/2000/09/xmldsig#enveloped-signature" /><Transform Algorithm="http://www.w3.org/TR/2001/REC-xml-c14n-20010315" /></Transforms><DigestMethod Algorithm="http://www.w3.org/2000/09/xmldsig#sha1" /><DigestValue>PAZC7F9Ex/BKafLsmd2JOy0qpzY=</DigestValue></Reference></SignedInfo><SignatureValue>RFEHRSpHPcBFjOy/ep52w2+UU+BdCU6F1nfwQDoks+hh6FH24ehi5yAt+UeJXkjUArpiu+9H5Olb
dDigsugANwt7sUIbQWlRUSmPHwgsGPNBVv1cEVHNCjbjdHnlXpoDxo5xVt778vjFAmYeOwPgUb2p
egQOtPQdoUj1pPBr0UUzSpslGu7TZNWZB1LRa/FJPk/RVjHwaYiU6wuPdG5eNQReSglsR78GrfYN
murzNBQZPJ+zetZ4kIu0eEya7ugiGgFlgdOpXzQNdcYOCEwi8LRCpwerIvq7myYjLBqVY0lC1nT6
4/5G1oC42qwqjy+3o5Nrz9ZxrRCRLO1jfdwP0w==</SignatureValue><KeyInfo><X509Data><X509Certificate>MIIH/jCCBeagAwIBAgIQXgA/qyCO6HZlBCuS8Mc93jANBgkqhkiG9w0BAQsFADB4MQswCQYDVQQG
EwJCUjETMBEGA1UEChMKSUNQLUJyYXNpbDE2MDQGA1UECxMtU2VjcmV0YXJpYSBkYSBSZWNlaXRh
IEZlZGVyYWwgZG8gQnJhc2lsIC0gUkZCMRwwGgYDVQQDExNBQyBDZXJ0aXNpZ24gUkZCIEc1MB4X
DTIxMDYyNTIwMjQyMloXDTIyMDYyNTIwMjQyMlowge0xCzAJBgNVBAYTAkJSMRMwEQYDVQQKDApJ
Q1AtQnJhc2lsMQswCQYDVQQIDAJTUDESMBAGA1UEBwwJU2FvIFBhdWxvMRMwEQYDVQQLDApQcmVz
ZW5jaWFsMRcwFQYDVQQLDA4wMjE3Mjk4MTAwMDE4MDE2MDQGA1UECwwtU2VjcmV0YXJpYSBkYSBS
ZWNlaXRhIEZlZGVyYWwgZG8gQnJhc2lsIC0gUkZCMRYwFAYDVQQLDA1SRkIgZS1DTlBKIEExMSow
KAYDVQQDDCFORVNUTEUgQlJBU0lMIExUREE6NjA0MDkwNzUwMDAxNTIwggEiMA0GCSqGSIb3DQEB
AQUAA4IBDwAwggEKAoIBAQClZhAhP1zOsmSKoAyoco3l+SLWMOxTEyiQnL+koqsrchIOJYEFLBny
tDNtdcwWM4GfxsyZujVmQD+MkxDjzXRO9FwkD79pUXsR2z2mNJcZnaxSfyF2x6bPLmOtYRaQ6gth
vRuahOtABglm2Miw1H1AskktxGyR8sh7DNj14aqEKmbmaGb5z0Ir2W6RHCsJMPgrJ0kLOj4YNYZ9
dl9JptEqIU9MBbQssKMHPUvtTpKw16AJdvQ/wo2EDgYkb2fpc80H/IQsO01kaqEfXDuDScGXsaer
jYtcJ8qUAqUecmhWogsf/fsky8EdHY2wY3ERcFLFoT+xDScOZUNuANNCqbmZAgMBAAGjggMMMIID
CDCBuwYDVR0RBIGzMIGwoDgGBWBMAQMEoC8ELTE2MDkxOTc4NzE2NTM0MDAxNzAwMDAwMDAwMDAw
MDAwMDAwMDAwMDAwMDAwMKAhBgVgTAEDAqAYBBZSVUkgUEVEUk8gVkFSRUxBIFJBTU9ToBkGBWBM
AQMDoBAEDjYwNDA5MDc1MDAwMTUyoBcGBWBMAQMHoA4EDDAwMDAwMDAwMDAwMIEdRkVSTkFOREEu
U0lMVkEyQEJSLk5FU1RMRS5DT00wCQYDVR0TBAIwADAfBgNVHSMEGDAWgBRTfX+dvtFh0CC62p/j
iacTc1jNQjB/BgNVHSAEeDB2MHQGBmBMAQIBDDBqMGgGCCsGAQUFBwIBFlxodHRwOi8vaWNwLWJy
YXNpbC5jZXJ0aXNpZ24uY29tLmJyL3JlcG9zaXRvcmlvL2RwYy9BQ19DZXJ0aXNpZ25fUkZCL0RQ
Q19BQ19DZXJ0aXNpZ25fUkZCLnBkZjCBvAYDVR0fBIG0MIGxMFegVaBThlFodHRwOi8vaWNwLWJy
YXNpbC5jZXJ0aXNpZ24uY29tLmJyL3JlcG9zaXRvcmlvL2xjci9BQ0NlcnRpc2lnblJGQkc1L0xh
dGVzdENSTC5jcmwwVqBUoFKGUGh0dHA6Ly9pY3AtYnJhc2lsLm91dHJhbGNyLmNvbS5ici9yZXBv
c2l0b3Jpby9sY3IvQUNDZXJ0aXNpZ25SRkJHNS9MYXRlc3RDUkwuY3JsMA4GA1UdDwEB/wQEAwIF
4DAdBgNVHSUEFjAUBggrBgEFBQcDAgYIKwYBBQUHAwQwgawGCCsGAQUFBwEBBIGfMIGcMF8GCCsG
AQUFBzAChlNodHRwOi8vaWNwLWJyYXNpbC5jZXJ0aXNpZ24uY29tLmJyL3JlcG9zaXRvcmlvL2Nl
cnRpZmljYWRvcy9BQ19DZXJ0aXNpZ25fUkZCX0c1LnA3YzA5BggrBgEFBQcwAYYtaHR0cDovL29j
c3AtYWMtY2VydGlzaWduLXJmYi5jZXJ0aXNpZ24uY29tLmJyMA0GCSqGSIb3DQEBCwUAA4ICAQBC
oXlZuagpS84zeWX10TcUrq8uBBWM0QmMXC2fH7J2ks2jCY0XNGZIgc5Dh1XqtNx5QmuspILm8Jds
0ECipCtR/hHiEVUyk0GdzPfSOBfxMzEBT4G6xi2fPpjkNbE2qjA0raEjCT4hjh+zwL6py/1+Jkcc
ABqqEJ925T6dLmGdMR6d54XjpKZR5AOF25ObC7kmX6pMC0+MVwsJzBqzS6avs/0hjUh0BI4tRxJg
pVaOZfNQSIHVt4XA9yEUNFNqulA9yEReUHvsU8bjuNnTg15IgfkWzfOxCokZRq9t/fIlYCihXDyO
pIuDHAllvjH6D8b8Om3EkM7e+L7iA1VPDs9XJHDdCFRelnxWNbnFhhoPR2CRvbnpxhfiyxevCevC
YDnx7RZXSUKDBDizXcGVSR3Ji2+japX7JoXGcBqqtm/VDsAR0dKLek6kJvy2VNS29yxryLA8+SrC
Fd1uIGfnLMuGVISqSltpZBoBeGYvqhjlWYZkyqndssqmJ2sYqEDMXHN13trSa+Utst/K3MtVbJve
C0Wa0bKScwSniUytpXGAJQVYLhC3HkrfG1ckHTN5swjdrRZScls6EosU5ja93Zw7dlSFSnzuiFx9
ZZScjJuWhDdDma5Q+CQ6oLHEAHzsWSPzgu6+8P8qaVxvOvtswiYd5aDIlrfyh5rsnBwe6KIIlA==</X509Certificate></X509Data></KeyInfo></Signature></NFe><protNFe versao="4.00"><infProt Id="ID131214272134752">
  <tpAmb>1</tpAmb>
  <verAplic>14.4.26-AC1</verAplic>
  <chNFe>31210760409075020340550010011847691058250939</chNFe>
  <dhRecbto>2021-07-31T09:53:29-03:00</dhRecbto>
  <nProt>131214272134752</nProt>
  <digVal>PAZC7F9Ex/BKafLsmd2JOy0qpzY=</digVal>
  <cStat>100</cStat>
  <xMotivo>Autorizado o uso da NF-e</xMotivo>
</infProt></protNFe></nfeProc>